Workbook

Sheet 00_INSTRUCCIONES
A1: PLANILLA MAESTRA DE EVALUACIÓN — TFG
A3: Propósito | B3: Esta planilla es el instrumento práctico de evaluación del TFG. Reúne las evidencias del baseline y del pipeline IA, aplica las métricas definidas en los capítulos 4 y 5, y calcula los resultados que después se explican en el capítulo de análisis.
A4: Alcance | B4: Política híbrida de evaluación: 7 evaluaciones R1 baseline (una por familia, con Seguimiento agregado en una fila por sprint) + 21 evaluaciones R1 pipeline (7 familias × 3 runs) = 28 evaluaciones R1 totales.
A5: Cómo usar (orden) | B5: 1) Revisar 01_A1_A2_inventario (A1/A2: artefactos IA y baseline). 2) Completar 02_R1_sintesis_artefactos y sus subinstrumentos R1: 03_R1_M1_checklist, 03b_R1_M1_resumen, 04_R1_M4_items y 05_R1_M3_contradicciones. 3) Revisar 06_P1_P2_pruebas (P1 validación técnica final + P2 checklist funcional). 4) Revisar 07_T1_T2_T3_tiempos (T1 ejecución automática IA, T2 esfuerzo humano/gate IA, T3 tiempos baseline). 5) Revisar 08_I1_incidencias (I1 incidencias). 6) Revisar 09_VD5_reproducibilidad (métricas M19-M21 derivadas de evidencias del caso IA). 7) Usar 10_AGREGADOS como lectura consolidada; algunas interpretaciones siguen requiriendo juicio cualitativo.
A7: Mapa de hojas, métricas y variables.
A8: Hoja | B8: Métricas | C8: VD | D8: Hipótesis / Rol
A9: 02_R1_sintesis_artefactos (+ 03, 03b, 04, 05) | B9: M1, M3, M4, M5 | C9: VD1 | D9: H2 (M1, M3, M4); M5 paralela, no contrasta H2
A10: 06_P1_P2_pruebas | B10: M6, M7, M-operatividad | C10: VD2 | D10: Criterio mínimo de comparabilidad, sin hipótesis
A11: 07_T1_T2_T3_tiempos | B11: M17 principal; M15, M18 auxiliares; M16 descriptiva | C11: VD4 | D11: H1
A12: 08_I1_incidencias | B12: M14 principal; M9, M10, M11, M12 auxiliares; M13 descriptiva | C12: VD3 | D12: H3
A13: 09_VD5_reproducibilidad | B13: M19, M20, M21 | C13: VD5 | D13: Caracterización del caso IA, sin hipótesis
A14: 08b_aux_bitacora_decisiones | B14: — | C14: — | D14: Bitácora del instrumento; no contrasta hipótesis
A16: Código de colores | B16: Amarillo = celda manual (input). Verde = celda calculada. Azul claro = pipeline. Naranja claro = baseline.
A17: Rúbricas y escalas. | B17: 1) M1 ordinal 0–3: 0 ausente, 1 parcial (<50 % o falta esencial), 2 sustancial (50–90 %), 3 completo (≥90 % + todos los esenciales). 2) M3 ordinal 0–3: 0 contradictorio (factual mayor o ≥3 contradicciones núcleo), 1 inconsistente (factual menor o 2–3 tipos), 2 coherente con fallos menores (≤2 terminológicas/granularidad), 3 coherente. 3) M4 porcentaje con cuatro tramos: 0–25 ausente/residual, 25–50 parcial, 50–75 sustancial, 75–100 alta. 4) M5 ordinal 0–4: suma directa de G1 (decisión), G2 (cambio), G3 (incidencia), G4 (aprobación/gate). 5) M-operatividad: 0 no arranca, 1 arranca pero flujo incompleto, 2 arranca y flujo mínimo completo.
A18: Reglas de evaluación | B18: 1) Regla 7 (cap. 4): toda evidencia se etiqueta como Original, Reconstruida o No disponible. 2) Criterio conservador (regla 3 del Anexo C): ante ambigüedad, contar como NO satisfecho y anotar. 3) Matching M4 baseline: textual con ≥3 palabras clave del dominio o mención literal de la función. 4) Matching M4 pipeline: ID explícito (booleano). 5) Si N < 3 ítems en una familia, M4 no se calcula; se reporta como tal. 6) Incidencias sistemáticas del pipeline (patrones replicados en los tres runs) se contabilizan una sola vez por patrón, marcando los runs afectados. (O: «se contabilizan una vez por run», según decidas).
A19: Hipótesis y criterio de veredicto. | B19: 1) H1 (VD4): confirmada si M17 pipeline < M17 baseline. Parcialmente sostenida si la ventaja existe pero depende de reconstrucción con incertidumbre. 2) H2 (VD1): confirmada si no aparece diferencia sustantiva desfavorable en M1/M3/M4 a través de las cinco familias. Parcialmente sostenida si la desventaja queda acotada a una dimensión. Rechazada si afecta a varias dimensiones. 3) H3 (VD3): confirmada si M14 pipeline < M14 baseline y M13 > 50 % (más de la mitad detectadas en gate humano). 4) VD2, VD5 y métricas descriptivas no tienen veredicto de hipótesis.

Sheet 01_A1_A2_inventario
A1: A1/A2 — Inventario maestro de artefactos IA y baseline
A3: ID | B3: Caso | C3: Run | D3: Familia | E3: Artefacto | F3: Ruta | G3: Regla 7 (Original / Reconstr. / No disp.) | H3: Estado evaluación | I3: Observaciones
A4: ART-B-REQ | B4: Baseline | C4: — | D4: Requisitos | E4: Registro Requisitos + Matriz Trazabilidad | F4: resultados_baseline\REGISTRO DE REQUISITOS.pdf + resultados_baseline\MATRIZ TRAZABILIDAD DE REQUISITOS.pdf | G4: Original | H4: Evaluado | I4: Fuente completa baseline localizada en 04_codigo/04a_casoBase/documentacion: REGISTRO DE REQUISITOS.pdf y MATRIZ TRAZABILIDAD DE REQUISITOS.pdf. Actas Patrocinador 1-4 sirven como evidencia auxiliar de cambios y aceptacion de alcance.
A5: ART-B-PLAN | B5: Baseline | C5: — | D5: Planificación | E5: Sprint Plannings + Product Backlogs S1-S2-S3 | F5: resultados_baseline\Sprint 1 - Planning.pdf + resultados_baseline\Sprint 2 - Planning.pdf + resultados_baseline\Sprint 3 - Planning.pdf + resultados_baseline\Sprint 1 - Product Backlog.pdf + resultados_baseline\Sprint 2 - Product Backlog.pdf + resultados_baseline\Sprint 3 - Product Backlog.pdf | G5: Original | H5: Evaluado | I5: Familia agregada: 3 sprints evaluados como conjunto. Fuente completa baseline localizada en documentacion/EJECUCION/Sprint 1-3. Fuentes auxiliares H1/planificacion: REGISTRO DE RIESGOS, CRONOGRAMA Y PRESUPUESTO, DICCIONARIO EDT, ATRIBUTOS DE ACTIVIDAD y PLAN DE GESTION DEL CRONOGRAMA.
A6: ART-B-DIS | B6: Baseline | C6: — | D6: Diseño técnico | E6: Auditoría posthoc 02_ARQUITECTURA + 03_MODELO_DATOS | F6: resultados_baseline\02_ARQUITECTURA.md + resultados_baseline\03_MODELO_DE_DATOS.md | G6: Reconstruida | H6: Evaluado | I6: Asimetria estructural mayor: baseline no produjo diseno tecnico original. Evidencia reconstruida principal y auxiliar localizada en documentacion/DISENO TECNICO (RECONSTRUIDO).
A7: ART-B-SEG-S1 | B7: Baseline | C7: — | D7: Seguimiento | E7: Sprint Review 1 + Retrospective 1 | F7: resultados_baseline\Sprint 1 - Review.pdf + resultados_baseline\Sprint 1 - Retrospetive.pdf | G7: Original | H7: Evaluado | I7: Fuente completa baseline: 04_codigo\04a_casoBase\documentacion\EJECUCIÓN\Sprint 1\Sprint 1 - Review.pdf + 04_codigo\04a_casoBase\documentacion\EJECUCIÓN\Sprint 1\Sprint 1 - Retrospetive.pdf. Evidencia auxiliar de gobernanza/incidencias: 04_codigo\04a_casoBase\documentacion\EJECUCIÓN\REGISTRO DE INCIDENCIAS.pdf + 04_codigo\04a_casoBase\documentacion\EJECUCIÓN\REGISTRO DE CAMBIOS.pdf + 04_codigo\04a_casoBase\documentacion\EJECUCIÓN\REGISTRO DE DECISIONES.pdf + 04_codigo\04a_casoBase\documentacion\SEGUIMIENTO\Daily Scrum Sprint 1.pdf + 04_codigo\04a_casoBase\documentacion\SEGUIMIENTO\Daily Scrum Sprint 2.pdf + 04_codigo\04a_casoBase\documentacion\SEGUIMIENTO\Daily Scrum Sprint 3.pdf.
A8: ART-B-SEG-S2 | B8: Baseline | C8: — | D8: Seguimiento | E8: Sprint Review 2 + Retrospective 2 | F8: resultados_baseline\Sprint 2 - Review.pdf + resultados_baseline\Sprint 2 - Retrospetive.pdf | G8: Original | H8: Evaluado | I8: Fuente completa baseline: 04_codigo\04a_casoBase\documentacion\EJECUCIÓN\Sprint 2\Sprint 2 - Review.pdf + 04_codigo\04a_casoBase\documentacion\EJECUCIÓN\Sprint 2\Sprint 2 - Retrospetive.pdf. Evidencia auxiliar de gobernanza/incidencias: 04_codigo\04a_casoBase\documentacion\EJECUCIÓN\REGISTRO DE INCIDENCIAS.pdf + 04_codigo\04a_casoBase\documentacion\EJECUCIÓN\REGISTRO DE CAMBIOS.pdf + 04_codigo\04a_casoBase\documentacion\EJECUCIÓN\REGISTRO DE DECISIONES.pdf + 04_codigo\04a_casoBase\documentacion\SEGUIMIENTO\Daily Scrum Sprint 1.pdf + 04_codigo\04a_casoBase\documentacion\SEGUIMIENTO\Daily Scrum Sprint 2.pdf + 04_codigo\04a_casoBase\documentacion\SEGUIMIENTO\Daily Scrum Sprint 3.pdf.
A9: ART-B-SEG-S3 | B9: Baseline | C9: — | D9: Seguimiento | E9: Sprint Review 3 + Retrospective 3 | F9: resultados_baseline\Sprint 3 - Review.pdf + resultados_baseline\Sprint 3 - Retrospetive.pdf | G9: Original | H9: Evaluado | I9: Fuente completa baseline: 04_codigo\04a_casoBase\documentacion\EJECUCIÓN\Sprint 3\Sprint 3 - Review.pdf + 04_codigo\04a_casoBase\documentacion\EJECUCIÓN\Sprint 3\Sprint 3 - Retrospetive.pdf. Evidencia auxiliar de gobernanza/incidencias: 04_codigo\04a_casoBase\documentacion\EJECUCIÓN\REGISTRO DE INCIDENCIAS.pdf + 04_codigo\04a_casoBase\documentacion\EJECUCIÓN\REGISTRO DE CAMBIOS.pdf + 04_codigo\04a_casoBase\documentacion\EJECUCIÓN\REGISTRO DE DECISIONES.pdf + 04_codigo\04a_casoBase\documentacion\SEGUIMIENTO\Daily Scrum Sprint 1.pdf + 04_codigo\04a_casoBase\documentacion\SEGUIMIENTO\Daily Scrum Sprint 2.pdf + 04_codigo\04a_casoBase\documentacion\SEGUIMIENTO\Daily Scrum Sprint 3.pdf.
A10: ART-B-CIE | B10: Baseline | C10: — | D10: Cierre | E10: Lecciones Aprendidas + Informe de cierre | F10: resultados_baseline\Lecciones aprendidas.pdf + resultados_baseline\Informe de cierre.pdf | G10: Original | H10: Evaluado | I10: Fuente completa baseline: 04_codigo\04a_casoBase\documentacion\CIERRE\Lecciones aprendidas.pdf + 04_codigo\04a_casoBase\documentacion\CIERRE\Informe de cierre.pdf. Evidencia auxiliar de cierre/seguimiento: 04_codigo\04a_casoBase\documentacion\SEGUIMIENTO\Cierre\Informe de Seguimiento - Cierre.pdf + 04_codigo\04a_casoBase\documentacion\SEGUIMIENTO\Cierre\Valor Ganado Cierre.pdf + 04_codigo\04a_casoBase\documentacion\SEGUIMIENTO\Cierre\Informe de Costos - Cierre.pdf + 04_codigo\04a_casoBase\documentacion\CIERRE\PROJECT CIERRE.pdf.
A11: ART-run_01-REQ | B11: Pipeline | C11: run_01 | D11: Requisitos | E11: registro_requisitos.json + .md | F11: resultados_pipeline\IA_OFICIAL_01\02_artefactos_generados\registro_requisitos.json + resultados_pipeline\IA_OFICIAL_01\02_artefactos_generados\registro_requisitos.md | G11: Original | H11: Evaluado
A12: ART-run_01-PLAN | B12: Pipeline | C12: run_01 | D12: Planificación | E12: backlog + plan_sprints + riesgos | F12: resultados_pipeline\IA_OFICIAL_01\02_artefactos_generados\backlog.json + resultados_pipeline\IA_OFICIAL_01\02_artefactos_generados\plan_sprints.json + resultados_pipeline\IA_OFICIAL_01\02_artefactos_generados\riesgos.json (+ versiones .md) | G12: Original | H12: Evaluado
A13: ART-run_01-DIS | B13: Pipeline | C13: run_01 | D13: Diseño técnico | E13: diseno_tecnico.json + .md | F13: resultados_pipeline\IA_OFICIAL_01\02_artefactos_generados\diseno_tecnico.json + resultados_pipeline\IA_OFICIAL_01\02_artefactos_generados\diseno_tecnico.md | G13: Original | H13: Evaluado
A14: ART-run_01-SEG-S1 | B14: Pipeline | C14: run_01 | D14: Seguimiento | E14: review_sprint_1.json + .md | F14: resultados_pipeline\IA_OFICIAL_01\03_sprints\review_sprint_1.json + resultados_pipeline\IA_OFICIAL_01\03_sprints\review_sprint_1.md | G14: Original | H14: Evaluado
A15: ART-run_01-SEG-S2 | B15: Pipeline | C15: run_01 | D15: Seguimiento | E15: review_sprint_2.json + .md | F15: resultados_pipeline\IA_OFICIAL_01\03_sprints\review_sprint_2.json + resultados_pipeline\IA_OFICIAL_01\03_sprints\review_sprint_2.md | G15: Original | H15: Evaluado
A16: ART-run_01-SEG-S3 | B16: Pipeline | C16: run_01 | D16: Seguimiento | E16: review_sprint_3.json + .md | F16: resultados_pipeline\IA_OFICIAL_01\03_sprints\review_sprint_3.json + resultados_pipeline\IA_OFICIAL_01\03_sprints\review_sprint_3.md | G16: Original | H16: Evaluado
A17: ART-run_01-CIE | B17: Pipeline | C17: run_01 | D17: Cierre | E17: lecciones_aprendidas.md + review_final.md + readme.md | F17: resultados_pipeline\IA_OFICIAL_01\04_cierre\lecciones_aprendidas.md + resultados_pipeline\IA_OFICIAL_01\00_manifest\review_final.md + resultados_pipeline\IA_OFICIAL_01\04_cierre\readme.md | G17: Original | H17: Evaluado
A18: ART-run_02-REQ | B18: Pipeline | C18: run_02 | D18: Requisitos | E18: registro_requisitos.json + .md | F18: resultados_pipeline\IA_OFICIAL_02\02_artefactos_generados\registro_requisitos.json + resultados_pipeline\IA_OFICIAL_02\02_artefactos_generados\registro_requisitos.md | G18: Original | H18: Evaluado
A19: ART-run_02-PLAN | B19: Pipeline | C19: run_02 | D19: Planificación | E19: backlog + plan_sprints + riesgos | F19: resultados_pipeline\IA_OFICIAL_02\02_artefactos_generados\backlog.json + resultados_pipeline\IA_OFICIAL_02\02_artefactos_generados\plan_sprints.json + resultados_pipeline\IA_OFICIAL_02\02_artefactos_generados\riesgos.json (+ versiones .md) | G19: Original | H19: Evaluado
A20: ART-run_02-DIS | B20: Pipeline | C20: run_02 | D20: Diseño técnico | E20: diseno_tecnico.json + .md | F20: resultados_pipeline\IA_OFICIAL_02\02_artefactos_generados\diseno_tecnico.json + resultados_pipeline\IA_OFICIAL_02\02_artefactos_generados\diseno_tecnico.md | G20: Original | H20: Evaluado
A21: ART-run_02-SEG-S1 | B21: Pipeline | C21: run_02 | D21: Seguimiento | E21: review_sprint_1.json + .md | F21: resultados_pipeline\IA_OFICIAL_02\03_sprints\review_sprint_1.json + resultados_pipeline\IA_OFICIAL_02\03_sprints\review_sprint_1.md | G21: Original | H21: Evaluado
A22: ART-run_02-SEG-S2 | B22: Pipeline | C22: run_02 | D22: Seguimiento | E22: review_sprint_2.json + .md | F22: resultados_pipeline\IA_OFICIAL_02\03_sprints\review_sprint_2.json + resultados_pipeline\IA_OFICIAL_02\03_sprints\review_sprint_2.md | G22: Original | H22: Evaluado
... A31: ART-run_03-CIE | B31: Pipeline | C31: run_03 | D31: Cierre | E31: lecciones_aprendidas.md + review_final.md + readme.md | F31: resultados_pipeline\IA_OFICIAL_03\04_cierre\lecciones_aprendidas.md + resultados_pipeline\IA_OFICIAL_03\00_manifest\review_final.md + resultados_pipeline\IA_OFICIAL_03\04_cierre\readme.md | G31: Original | H31: Evaluado

Sheet 03_R1_M1_checklist
A1: R1/M1 — Checklist por familia y artefacto (cobertura)
A2: Marca en cada columna SI el elemento está presente. Las columnas finales calculan cobertura. Esenciales con asterisco (*): si falta alguno, M1 baja a nivel 1.
A4: ID artefacto | B4: Familia | C4: Elemento esperado | D4: Esencial | E4: Presente (1/0) | F4: Evidencia (cita/ubicación)
A5: ART-B-REQ | B5: Requisitos | C5: Declaración de propósito / brief de referencia * | D5: Sí | E5: 1 | F5: 04_codigo\04a_casoBase\documentacion\PLANIFICACIÓN\REGISTROS\REGISTRO DE REQUISITOS.pdf + 04_codigo\04a_casoBase\documentacion\PLANIFICACIÓN\TRAZABILIDAD\MATRIZ TRAZABILIDAD DE REQUISITOS.pdf
A6: ART-B-REQ | B6: Requisitos | C6: Conjunto de RF con ID, descripción y prioridad * | D6: Sí | E6: 1 | F6: 04_codigo\04a_casoBase\documentacion\PLANIFICACIÓN\REGISTROS\REGISTRO DE REQUISITOS.pdf + 04_codigo\04a_casoBase\documentacion\PLANIFICACIÓN\TRAZABILIDAD\MATRIZ TRAZABILIDAD DE REQUISITOS.pdf
A7: ART-B-REQ | B7: Requisitos | C7: Conjunto de RNF con misma estructura * | D7: Sí | E7: 1 | F7: 04_codigo\04a_casoBase\documentacion\PLANIFICACIÓN\REGISTROS\REGISTRO DE REQUISITOS.pdf + 04_codigo\04a_casoBase\documentacion\PLANIFICACIÓN\TRAZABILIDAD\MATRIZ TRAZABILIDAD DE REQUISITOS.pdf
A8: ART-B-REQ | B8: Requisitos | C8: Cobertura mínima de funciones críticas del brief (auth/cat/reserva/admin) * | D8: Sí | E8: 1 | F8: 04_codigo\04a_casoBase\documentacion\PLANIFICACIÓN\REGISTROS\REGISTRO DE REQUISITOS.pdf + 04_codigo\04a_casoBase\documentacion\PLANIFICACIÓN\TRAZABILIDAD\MATRIZ TRAZABILIDAD DE REQUISITOS.pdf
A9: ART-B-REQ | B9: Requisitos | C9: Declaración explícita de exclusiones | D9: No | E9: 1 | F9: 04_codigo\04a_casoBase\documentacion\PLANIFICACIÓN\REGISTROS\REGISTRO DE REQUISITOS.pdf + 04_codigo\04a_casoBase\documentacion\PLANIFICACIÓN\TRAZABILIDAD\MATRIZ TRAZABILIDAD DE REQUISITOS.pdf + 04_codigo\04a_casoBase\documentacion\INICIO\ACTA DE CONSTITUCIÓN.pdf + 04_codigo\04a_casoBase\documentacion\INICIO\REGISTRO DE SUPUESTOS.pdf + 04_codigo\04a_casoBase\documentacion\PLANIFICACIÓN\LINEAS BASE\ENUNCIADO DEL ALCANCE.pdf
A10: ART-B-REQ | B10: Requisitos | C10: Registro de supuestos y restricciones | D10: No | E10: 1 | F10: 04_codigo\04a_casoBase\documentacion\PLANIFICACIÓN\REGISTROS\REGISTRO DE REQUISITOS.pdf + 04_codigo\04a_casoBase\documentacion\PLANIFICACIÓN\TRAZABILIDAD\MATRIZ TRAZABILIDAD DE REQUISITOS.pdf + 04_codigo\04a_casoBase\documentacion\INICIO\ACTA DE CONSTITUCIÓN.pdf + 04_codigo\04a_casoBase\documentacion\INICIO\REGISTRO DE SUPUESTOS.pdf + 04_codigo\04a_casoBase\documentacion\PLANIFICACIÓN\LINEAS BASE\ENUNCIADO DEL ALCANCE.pdf
A11: ART-B-REQ | B11: Requisitos | C11: Criterios genéricos de aceptación a nivel de proyecto | D11: No | E11: 1 | F11: 04_codigo\04a_casoBase\documentacion\PLANIFICACIÓN\REGISTROS\REGISTRO DE REQUISITOS.pdf + 04_codigo\04a_casoBase\documentacion\PLANIFICACIÓN\TRAZABILIDAD\MATRIZ TRAZABILIDAD DE REQUISITOS.pdf
A12: ART-B-PLAN | B12: Planificación | C12: Descomposición del alcance en HU con ID/descripción/prioridad * | D12: Sí | E12: 0 | F12: 04_codigo\04a_casoBase\documentacion\EJECUCIÓN\Sprint 1\Sprint 1 - Planning.pdf + 04_codigo\04a_casoBase\documentacion\EJECUCIÓN\Sprint 2\Sprint 2 - Planning.pdf + 04_codigo\04a_casoBase\documentacion\EJECUCIÓN\Sprint 3\Sprint 3 - Planning.pdf + 04_codigo\04a_casoBase\documentacion\EJECUCIÓN\Sprint 1\Sprint 1 - Product Backlog.pdf + 04_codigo\04a_casoBase\documentacion\EJECUCIÓN\Sprint 2\Sprint 2 - Product Backlog.pdf + 04_codigo\04a_casoBase\documentacion\EJECUCIÓN\Sprint 3\Sprint 3 - Product Backlog.pdf
A13: ART-B-PLAN | B13: Planificación | C13: Asignación de HU a sprints con objetivo declarado * | D13: Sí | E13: 0 | F13: 04_codigo\04a_casoBase\documentacion\EJECUCIÓN\Sprint 1\Sprint 1 - Planning.pdf + 04_codigo\04a_casoBase\documentacion\EJECUCIÓN\Sprint 2\Sprint 2 - Planning.pdf + 04_codigo\04a_casoBase\documentacion\EJECUCIÓN\Sprint 3\Sprint 3 - Planning.pdf + 04_codigo\04a_casoBase\documentacion\EJECUCIÓN\Sprint 1\Sprint 1 - Product Backlog.pdf + 04_codigo\04a_casoBase\documentacion\EJECUCIÓN\Sprint 2\Sprint 2 - Product Backlog.pdf + 04_codigo\04a_casoBase\documentacion\EJECUCIÓN\Sprint 3\Sprint 3 - Product Backlog.pdf
A14: ART-B-PLAN | B14: Planificación | C14: Entregable verificable por sprint * | D14: Sí | E14: 1 | F14: 04_codigo\04a_casoBase\documentacion\EJECUCIÓN\Sprint 1\Sprint 1 - Planning.pdf + 04_codigo\04a_casoBase\documentacion\EJECUCIÓN\Sprint 2\Sprint 2 - Planning.pdf + 04_codigo\04a_casoBase\documentacion\EJECUCIÓN\Sprint 3\Sprint 3 - Planning.pdf + 04_codigo\04a_casoBase\documentacion\EJECUCIÓN\Sprint 1\Sprint 1 - Product Backlog.pdf + 04_codigo\04a_casoBase\documentacion\EJECUCIÓN\Sprint 2\Sprint 2 - Product Backlog.pdf + 04_codigo\04a_casoBase\documentacion\EJECUCIÓN\Sprint 3\Sprint 3 - Product Backlog.pdf
A15: ART-B-PLAN | B15: Planificación | C15: Estimación de esfuerzo por HU * | D15: Sí | E15: 0 | F15: 04_codigo\04a_casoBase\documentacion\EJECUCIÓN\Sprint 1\Sprint 1 - Planning.pdf + 04_codigo\04a_casoBase\documentacion\EJECUCIÓN\Sprint 2\Sprint 2 - Planning.pdf + 04_codigo\04a_casoBase\documentacion\EJECUCIÓN\Sprint 3\Sprint 3 - Planning.pdf + 04_codigo\04a_casoBase\documentacion\EJECUCIÓN\Sprint 1\Sprint 1 - Product Backlog.pdf + 04_codigo\04a_casoBase\documentacion\EJECUCIÓN\Sprint 2\Sprint 2 - Product Backlog.pdf + 04_codigo\04a_casoBase\documentacion\EJECUCIÓN\Sprint 3\Sprint 3 - Product Backlog.pdf
A16: ART-B-PLAN | B16: Planificación | C16: Registro de riesgos con probabilidad/impacto/mitigación * | D16: Sí | E16: 1 | F16: 04_codigo\04a_casoBase\documentacion\EJECUCIÓN\Sprint 1\Sprint 1 - Planning.pdf + 04_codigo\04a_casoBase\documentacion\EJECUCIÓN\Sprint 2\Sprint 2 - Planning.pdf + 04_codigo\04a_casoBase\documentacion\EJECUCIÓN\Sprint 3\Sprint 3 - Planning.pdf + 04_codigo\04a_casoBase\documentacion\EJECUCIÓN\Sprint 1\Sprint 1 - Product Backlog.pdf + 04_codigo\04a_casoBase\documentacion\EJECUCIÓN\Sprint 2\Sprint 2 - Product Backlog.pdf + 04_codigo\04a_casoBase\documentacion\EJECUCIÓN\Sprint 3\Sprint 3 - Product Backlog.pdf + 04_codigo\04a_casoBase\documentacion\PLANIFICACIÓN\REGISTROS\REGISTRO DE RIESGOS.pdf
... A50: ART-B-CIE | B50: Cierre | C50: Identificación de causas raíz | D50: No | E50: 0 | F50: 04_codigo\04a_casoBase\documentacion\CIERRE\Lecciones aprendidas.pdf + 04_codigo\04a_casoBase\documentacion\CIERRE\Informe de cierre.pdf + 04_codigo\04a_casoBase\documentacion\SEGUIMIENTO\Cierre\Informe de Seguimiento - Cierre.pdf + 04_codigo\04a_casoBase\documentacion\SEGUIMIENTO\Cierre\Valor Ganado Cierre.pdf + 04_codigo\04a_casoBase\documentacion\SEGUIMIENTO\Cierre\Informe de Costos - Cierre.pdf + 04_codigo\04a_casoBase\documentacion\CIERRE\PROJECT CIERRE.pdf
A51: ART-run_01-REQ | B51: Requisitos | C51: Declaración de propósito / brief de referencia * | D51: Sí | E51: 1
A52: ART-run_01-REQ | B52: Requisitos | C52: Conjunto de RF con ID, descripción y prioridad * | D52: Sí | E52: 1
A53: ART-run_01-REQ | B53: Requisitos | C53: Conjunto de RNF con misma estructura * | D53: Sí | E53: 1
A54: ART-run_01-REQ | B54: Requisitos | C54: Cobertura mínima de funciones críticas del brief (auth/cat/reserva/admin) * | D54: Sí | E54: 1
A55: ART-run_01-REQ | B55: Requisitos | C55: Declaración explícita de exclusiones | D55: No | E55: 0
A56: ART-run_01-REQ | B56: Requisitos | C56: Registro de supuestos y restricciones | D56: No | E56: 0
A57: ART-run_01-REQ | B57: Requisitos | C57: Criterios genéricos de aceptación a nivel de proyecto | D57: No | E57: 0
A58: ART-run_01-PLAN | B58: Planificación | C58: Descomposición del alcance en HU con ID/descripción/prioridad * | D58: Sí | E58: 1
A59: ART-run_01-PLAN | B59: Planificación | C59: Asignación de HU a sprints con objetivo declarado * | D59: Sí | E59: 1
A60: ART-run_01-PLAN | B60: Planificación | C60: Entregable verificable por sprint * | D60: Sí | E60: 1
A61: ART-run_01-PLAN | B61: Planificación | C61: Estimación de esfuerzo por HU * | D61: Sí | E61: 0
A62: ART-run_01-PLAN | B62: Planificación | C62: Registro de riesgos con probabilidad/impacto/mitigación * | D62: Sí | E62: 1
... A188: ART-run_03-CIE | B188: Cierre | C188: Identificación de causas raíz | D188: No | E188: 0

Sheet 03b_R1_M1_resumen
A1: R1/M1 — Resumen automático de cobertura por artefacto
A3: ID artefacto | B3: Caso | C3: Familia | D3: N total elementos | E3: N satisfechos | F3: Cobertura (%) | G3: N esenciales | H3: Esenciales satisfechos | I3: Nivel M1 (calculado)
A4: ART-B-REQ | B4: Baseline | C4: Requisitos | D4: 7 | E4: =SUMIFS('03_R1_M1_checklist'!E:E,'03_R1_M1_checklist'!A:A,A4) | F4: =IF(D4>0,E4/D4*100,0) | G4: 4 | H4: =COUNTIFS('03_R1_M1_checklist'!A:A,A4,'03_R1_M1_checklist'!D:D,"Sí",'03_R1_M1_checklist'!E:E,1) | I4: =IF(E4="",0,IF(AND(F4>=90,H4=G4),3,IF(AND(F4>=50,H4=G4),2,IF(E4>0,1,0))))
A5: ART-B-PLAN | B5: Baseline | C5: Planificación | D5: 8 | E5: =SUMIFS('03_R1_M1_checklist'!E:E,'03_R1_M1_checklist'!A:A,A5) | F5: =IF(D5>0,E5/D5*100,0) | G5: 5 | H5: =COUNTIFS('03_R1_M1_checklist'!A:A,A5,'03_R1_M1_checklist'!D:D,"Sí",'03_R1_M1_checklist'!E:E,1) | I5: =IF(E5="",0,IF(AND(F5>=90,H5=G5),3,IF(AND(F5>=50,H5=G5),2,IF(E5>0,1,0))))
A6: ART-B-DIS | B6: Baseline | C6: Diseño técnico | D6: 7 | E6: =SUMIFS('03_R1_M1_checklist'!E:E,'03_R1_M1_checklist'!A:A,A6) | F6: =IF(D6>0,E6/D6*100,0) | G6: 4 | H6: =COUNTIFS('03_R1_M1_checklist'!A:A,A6,'03_R1_M1_checklist'!D:D,"Sí",'03_R1_M1_checklist'!E:E,1) | I6: =IF(E6="",0,IF(AND(F6>=90,H6=G6),3,IF(AND(F6>=50,H6=G6),2,IF(E6>0,1,0))))
A7: ART-B-SEG-S1 | B7: Baseline | C7: Seguimiento | D7: 6 | E7: =SUMIFS('03_R1_M1_checklist'!E:E,'03_R1_M1_checklist'!A:A,A7) | F7: =IF(D7>0,E7/D7*100,0) | G7: 4 | H7: =COUNTIFS('03_R1_M1_checklist'!A:A,A7,'03_R1_M1_checklist'!D:D,"Sí",'03_R1_M1_checklist'!E:E,1) | I7: =IF(E7="",0,IF(AND(F7>=90,H7=G7),3,IF(AND(F7>=50,H7=G7),2,IF(E7>0,1,0))))
A8: ART-B-SEG-S2 | B8: Baseline | C8: Seguimiento | D8: 6 | E8: =SUMIFS('03_R1_M1_checklist'!E:E,'03_R1_M1_checklist'!A:A,A8) | F8: =IF(D8>0,E8/D8*100,0) | G8: 4 | H8: =COUNTIFS('03_R1_M1_checklist'!A:A,A8,'03_R1_M1_checklist'!D:D,"Sí",'03_R1_M1_checklist'!E:E,1) | I8: =IF(E8="",0,IF(AND(F8>=90,H8=G8),3,IF(AND(F8>=50,H8=G8),2,IF(E8>0,1,0))))
A9: ART-B-SEG-S3 | B9: Baseline | C9: Seguimiento | D9: 6 | E9: =SUMIFS('03_R1_M1_checklist'!E:E,'03_R1_M1_checklist'!A:A,A9) | F9: =IF(D9>0,E9/D9*100,0) | G9: 4 | H9: =COUNTIFS('03_R1_M1_checklist'!A:A,A9,'03_R1_M1_checklist'!D:D,"Sí",'03_R1_M1_checklist'!E:E,1) | I9: =IF(E9="",0,IF(AND(F9>=90,H9=G9),3,IF(AND(F9>=50,H9=G9),2,IF(E9>0,1,0))))
A10: ART-B-CIE | B10: Baseline | C10: Cierre | D10: 6 | E10: =SUMIFS('03_R1_M1_checklist'!E:E,'03_R1_M1_checklist'!A:A,A10) | F10: =IF(D10>0,E10/D10*100,0) | G10: 4 | H10: =COUNTIFS('03_R1_M1_checklist'!A:A,A10,'03_R1_M1_checklist'!D:D,"Sí",'03_R1_M1_checklist'!E:E,1) | I10: =IF(E10="",0,IF(AND(F10>=90,H10=G10),3,IF(AND(F10>=50,H10=G10),2,IF(E10>0,1,0))))
A11: ART-run_01-REQ | B11: Pipeline | C11: Requisitos | D11: 7 | E11: =SUMIFS('03_R1_M1_checklist'!E:E,'03_R1_M1_checklist'!A:A,A11) | F11: =IF(D11>0,E11/D11*100,0) | G11: 4 | H11: =COUNTIFS('03_R1_M1_checklist'!A:A,A11,'03_R1_M1_checklist'!D:D,"Sí",'03_R1_M1_checklist'!E:E,1) | I11: =IF(E11="",0,IF(AND(F11>=90,H11=G11),3,IF(AND(F11>=50,H11=G11),2,IF(E11>0,1,0))))
A12: ART-run_01-PLAN | B12: Pipeline | C12: Planificación | D12: 8 | E12: =SUMIFS('03_R1_M1_checklist'!E:E,'03_R1_M1_checklist'!A:A,A12) | F12: =IF(D12>0,E12/D12*100,0) | G12: 5 | H12: =COUNTIFS('03_R1_M1_checklist'!A:A,A12,'03_R1_M1_checklist'!D:D,"Sí",'03_R1_M1_checklist'!E:E,1) | I12: =IF(E12="",0,IF(AND(F12>=90,H12=G12),3,IF(AND(F12>=50,H12=G12),2,IF(E12>0,1,0))))
A13: ART-run_01-DIS | B13: Pipeline | C13: Diseño técnico | D13: 7 | E13: =SUMIFS('03_R1_M1_checklist'!E:E,'03_R1_M1_checklist'!A:A,A13) | F13: =IF(D13>0,E13/D13*100,0) | G13: 4 | H13: =COUNTIFS('03_R1_M1_checklist'!A:A,A13,'03_R1_M1_checklist'!D:D,"Sí",'03_R1_M1_checklist'!E:E,1) | I13: =IF(E13="",0,IF(AND(F13>=90,H13=G13),3,IF(AND(F13>=50,H13=G13),2,IF(E13>0,1,0))))
A14: ART-run_01-SEG-S1 | B14: Pipeline | C14: Seguimiento | D14: 6 | E14: =SUMIFS('03_R1_M1_checklist'!E:E,'03_R1_M1_checklist'!A:A,A14) | F14: =IF(D14>0,E14/D14*100,0) | G14: 4 | H14: =COUNTIFS('03_R1_M1_checklist'!A:A,A14,'03_R1_M1_checklist'!D:D,"Sí",'03_R1_M1_checklist'!E:E,1) | I14: =IF(E14="",0,IF(AND(F14>=90,H14=G14),3,IF(AND(F14>=50,H14=G14),2,IF(E14>0,1,0))))
A15: ART-run_01-SEG-S2 | B15: Pipeline | C15: Seguimiento | D15: 6 | E15: =SUMIFS('03_R1_M1_checklist'!E:E,'03_R1_M1_checklist'!A:A,A15) | F15: =IF(D15>0,E15/D15*100,0) | G15: 4 | H15: =COUNTIFS('03_R1_M1_checklist'!A:A,A15,'03_R1_M1_checklist'!D:D,"Sí",'03_R1_M1_checklist'!E:E,1) | I15: =IF(E15="",0,IF(AND(F15>=90,H15=G15),3,IF(AND(F15>=50,H15=G15),2,IF(E15>0,1,0))))
... A31: ART-run_03-CIE | B31: Pipeline | C31: Cierre | D31: 6 | E31: =SUMIFS('03_R1_M1_checklist'!E:E,'03_R1_M1_checklist'!A:A,A31) | F31: =IF(D31>0,E31/D31*100,0) | G31: 4 | H31: =COUNTIFS('03_R1_M1_checklist'!A:A,A31,'03_R1_M1_checklist'!D:D,"Sí",'03_R1_M1_checklist'!E:E,1) | I31: =IF(E31="",0,IF(AND(F31>=90,H31=G31),3,IF(AND(F31>=50,H31=G31),2,IF(E31>0,1,0))))

Sheet 05_R1_M3_contradicciones
A1: R1/M3 — Registro de contradicciones detectadas
A2: Una fila por contradicción detectada. Tipos: Factual, Terminológica, Granularidad, Prioridad/estado. Mayor/Menor solo para factuales (mayor = afecta núcleo funcional, esencial del check-list de M1).
A4: ID artefacto | B4: ID contradicción | C4: Tipo | D4: Mayor/Menor (solo factual) | E4: Ubicación 1 | F4: Ubicación 2 | G4: Descripción | H4: Notas
A5: ART-B-REQ
A6: ART-B-REQ | B6: M3-B-REQ-01 | C6: Terminológica | E6: Registro de Requisitos (IDs RF13, RF15, RF19) | F6: Matriz de Trazabilidad (IDs RF13, RF15, RF19) | G6: RF13, RF15 y RF19 no aparecen con la misma identificación/etiqueta en ambos documentos: el mismo requisito recibe nomenclatura distinta entre Registro y Matriz.
A7: ART-B-REQ | B7: M3-B-REQ-02 | C7: Granularidad | E7: Registro de Requisitos (numeración tras RF16) | G7: La serie de identificadores salta numeración tras RF16, dejando huecos en la secuencia de RF; la lista de requisitos no mantiene un mismo nivel de granularidad en su indexación.
A8: ART-B-REQ | B8: M3-B-REQ-03 | C8: Granularidad | E8: Registro de Requisitos (RF19) | F8: Matriz de Trazabilidad / Product Backlogs S1-S3 | G8: RF19 queda sin correspondencia clara en Registro/backlogs: el requisito no se descompone ni se enlaza al mismo nivel de detalle que el resto.
A9: ART-B-PLAN
A10: ART-B-PLAN | B10: M3-B-PLAN-01 | C10: Terminológica | E10: Sprint Plannings S1-S2-S3 (encabezado / tipo documental) | G10: Algunos documentos de planning mantienen un tipo documental incorrecto en encabezado, confundiendo el rótulo del artefacto con su contenido.
A11: ART-B-PLAN | B11: M3-B-PLAN-02 | C11: Granularidad | E11: Sprint Planning Sx (decisión de pasarela/despliegue) | F11: Sprint Planning Sy / Informe de cierre | G11: Cambios de pasarela de pago y/o estrategia de despliegue entre sprints documentados a granularidad desigual: la decisión técnica no se refleja con el mismo nivel de detalle en plannings sucesivos, quedando solo parcialmente justificada en planning/cierre.
A13: ART-B-DIS
A17: ART-B-SEG-S1
A18: ART-B-SEG-S1 | B18: M3-B-SEG-S1-01 | C18: Terminológica | E18: Sprint Review 1 / Retrospective 1 (encabezado) | G18: Algunos encabezados identifican la review/retrospective como Sprint Planning: el mismo tipo de documento recibe rótulos distintos, lo que introduce ambigüedad sobre el tipo de artefacto. No afecta al contenido central.
A21: ART-B-SEG-S2
A22: ART-B-SEG-S2 | B22: M3-B-SEG-S2-01 | C22: Terminológica | E22: Sprint Review 2 / Retrospective 2 (encabezado) | G22: Encabezado/tipo de documento inconsistente con el contenido del artefacto: persiste la confusión Planning vs. Review/Retrospective del Sprint 1.
A25: ART-B-SEG-S3
A26: ART-B-SEG-S3 | B26: M3-B-SEG-S3-01 | C26: Factual | D26: Menor | E26: Retrospectiva Sprint 3 (fechas) | F26: Planning / Review Sprint 3 (fechas) | G26: Fechas declaradas en la retrospectiva del Sprint 3 no cuadran con las del planning/review del mismo sprint: dos elementos del artefacto afirman cosas incompatibles sobre el mismo aspecto temporal. Menor: no afecta al núcleo funcional del seguimiento.
A27: ART-B-SEG-S3 | B27: M3-B-SEG-S3-02 | C27: Terminológica | E27: Sprint Review 3 / Retrospective 3 (encabezado) | G27: Persistencia de encabezados no alineados con el tipo real de documento (Planning vs Review/Retrospective), análoga a S1 y S2.
A29: ART-B-CIE
A33: ART-run_01-REQ
A34: ART-run_01-REQ | B34: M3-run_01-REQ-01 | C34: Granularidad | E34: registro_requisitos.json / .md (campo prioridad) | G34: La priorización asignada a los RF/RNF es poco discriminante: la mayoría de los ítems recibe el mismo valor, lo que indica granularidad insuficiente en el atributo de prioridad. Observación no bloqueante registrada por Gate 1.
A35: ART-run_01-REQ | B35: M3-run_01-REQ-02 | C35: Granularidad | E35: registro_requisitos.json / .md (RNF de seguridad e importe) | G35: Granularidad limitada en los RNF de seguridad y de importe: requisitos que deberían desglosarse en varios ítems quedan agrupados en un único RNF.
A37: ART-run_01-PLAN
A38: ART-run_01-PLAN | B38: M3-run_01-PLAN-01 | C38: Granularidad | E38: backlog / plan_sprints (reparto entre sprints) | G38: Concentración de complejidad en un sprint frente a los otros: el reparto de HU no mantiene un nivel de complejidad homogéneo entre los tres sprints. Observación no bloqueante de Gate 2.
A39: ART-run_01-PLAN | B39: M3-run_01-PLAN-02 | C39: Granularidad | E39: Dockerfile (seed) / plan_sprints (uso de cron/Celery) | G39: Decisiones técnicas (seed en Dockerfile, posible exceso con cron/Celery) introducidas a un nivel de detalle distinto del que corresponde a un artefacto de planificación: mezcla de planificación de alto nivel con detalle de implementación. Observación no bloqueante de Gate 2.
A41: ART-run_01-DIS
A42: ART-run_01-DIS | B42: M3-run_01-DIS-01 | C42: Terminol?gica | E42: diseno_tecnico.json / .md (campo ImageField) | G42: ImageField aparece declarado como upload_to=barcos/ sin comillas; el dise?o usa una formulaci?n no alineada con la convenci?n del framework. Observaci?n menor de Gate 3.
A43: ART-run_01-DIS | B43: M3-run_01-DIS-02 | C43: Granularidad | E43: diseno_tecnico.json / .md (core/settings, core/urls) | G43: core/settings.py y core/urls.py pueden confundirse con el paquete de proyecto Django; la organizaci?n se documenta a un nivel distinto del resto de apps/componentes. Observaci?n menor de Gate 3.
A44: ART-run_01-DIS | B44: M3-run_01-DIS-03 | C44: Granularidad | E44: diseno_tecnico.json / .md (disponibilidad y rutas) | G44: La disponibilidad por fechas aparece tratada con menor precisi?n t?cnica de la esperada y logout se plantea como ruta GET; son observaciones de dise?o no bloqueantes registradas en Gate 3.
A45: ART-run_01-SEG-S1
A49: ART-run_01-SEG-S2
A53: ART-run_01-SEG-S3
A57: ART-run_01-CIE
A61: ART-run_02-REQ
A62: ART-run_02-REQ | B62: M3-run_02-REQ-01 | C62: Granularidad | E62: registro_requisitos.json / .md (roles) | G62: Los roles cliente y administrador no aparecen como requisito independiente, sino implícitos en otros ítems: omisión por granularidad insuficiente en la declaración de actores. Observación no bloqueante de Gate 1.
A65: ART-run_02-PLAN
A66: ART-run_02-PLAN | B66: M3-run_02-PLAN-01 | C66: Factual | D66: Menor | E66: plan_sprints (entregable Sprint 2) | F66: backlog (HU-16 asignada a Sprint 3) | G66: El entregable declarado para el Sprint 2 menciona la consulta por código, pero la HU-16 que materializa esa funcionalidad está asignada al Sprint 3: dos partes del artefacto afirman cosas incompatibles sobre cuándo se entrega esa funcionalidad. Menor: no afecta al núcleo del producto, solo a la planificación interna.
A69: ART-run_02-DIS
A70: ART-run_02-DIS | B70: M3-run_02-DIS-01 | C70: Terminológica | E70: diseno_tecnico.json / .md (campo ImageField) | G70: ImageField declarado como cadena en lugar de su tipo específico: el mismo concepto recibe una denominación de tipo distinta de la convención del framework. Observación menor de Gate 3.
A71: ART-run_02-DIS | B71: M3-run_02-DIS-02 | C71: Granularidad | E71: diseno_tecnico.json / .md (User propio, core/settings, disponibilidad por fechas) | G71: Observaciones técnicas agrupadas sobre granularidad desigual del diseño: User propio, organización de core/settings y cálculo de disponibilidad por fechas se documentan a niveles de detalle inconsistentes entre sí. Observaciones menores de Gate 3.
A73: ART-run_02-SEG-S1
A77: ART-run_02-SEG-S2
A81: ART-run_02-SEG-S3
A85: ART-run_02-CIE
A89: ART-run_03-REQ
A93: ART-run_03-PLAN
A94: ART-run_03-PLAN | B94: M3-run_03-PLAN-01 | C94: Granularidad | E94: plan_sprints / backlog (reparto y detalle) | G94: Observación menor de planificación señalada por Gate 2: el reparto/granularidad de algunos ítems del backlog presenta detalle desigual, sin llegar a incoherencia bloqueante.
A97: ART-run_03-DIS
A98: ART-run_03-DIS | B98: M3-run_03-DIS-01 | C98: Terminológica | E98: diseno_tecnico.json / .md (campo ImageField) | G98: ImageField declarado como cadena en lugar del tipo específico del framework: misma observación terminológica que en run_02. Observación menor de Gate 3.
A99: ART-run_03-DIS | B99: M3-run_03-DIS-02 | C99: Terminológica | E99: diseno_tecnico.json / .md (namespace admin) | F99: diseno_tecnico.json / .md (namespace admin_panel) | G99: El mismo concepto de panel de administración recibe dos nombres distintos en el diseño: admin y admin_panel, sin justificación. Observación menor de Gate 3.
A100: ART-run_03-DIS | B100: M3-run_03-DIS-03 | C100: Granularidad | E100: diseno_tecnico.json / .md (core/settings, cálculo de disponibilidad) | G100: Observaciones técnicas sobre granularidad desigual del diseño: organización de core/settings y cálculo de disponibilidad documentados a niveles de detalle inconsistentes. Observaciones menores de Gate 3.
A101: ART-run_03-SEG-S1
A105: ART-run_03-SEG-S2
A109: ART-run_03-SEG-S3
A113: ART-run_03-CIE

Sheet 04_R1_M4_items
A1: R1/M4 — Verificación ítem a ítem de trazabilidad
A2: Esta hoja documenta ítem a ítem los artefactos del baseline. La trazabilidad del pipeline se documenta mediante la capa automática descrita en el TFG y sus resultados agregados aparecen en las columnas K, L y M de 02_R1_sintesis_artefactos. Una fila por ítem del artefacto (RF/RNF/HU/etc.). Marca 1/0 si presenta enlace verificable aguas arriba y aguas abajo. Si la familia ocupa un extremo de la cadena, solo se exige una dirección.
A4: ID artefacto | B4: Item ID | C4: Item descripción corta | D4: Tipo matching (ID/textual) | E4: Aguas arriba (1/0) | F4: Aguas abajo (1/0) | G4: ¿Es extremo de cadena? (Si/No) | H4: Trazable (calc) | I4: Evidencia/cita | J4: Observaciones
A5: ART-B-REQ | B5: RF1 | C5: Barcos visibles para alquiler | D5: Textual | F5: 1 | G5: Sí | H5: =IF(F5=1,1,0) | I5: Matriz RF1 vincula barcos visibles con Front End y pruebas funcionales. Product Backlog S1/S2/S3 cita RF1 literal y lo marca Terminado.
A6: ART-B-REQ | B6: RNF1 | C6: Mecanismo simple para aumentar/disminuir tiempo de alquiler | D6: Textual | F6: 1 | G6: Sí | H6: =IF(F6=1,1,0) | I6: Matriz RNF1 vincula tiempo de alquiler con Front End y pruebas de satisfaccion. Product Backlog S1/S2/S3 cita RNF1 literal y lo marca Terminado.
A7: ART-B-REQ | B7: RF2 | C7: Categorias de barcos iguales a las que se ofertan | D7: Textual | F7: 1 | G7: Sí | H7: =IF(F7=1,1,0) | I7: Matriz RF2 vincula categorias de barcos con Front End/Back End. Product Backlog S1/S2/S3 cita RF2 literal y lo marca Terminado.
A8: ART-B-REQ | B8: RF3 | C8: Alquiler sin requerir inicio de sesion | D8: Textual | F8: 1 | G8: Sí | H8: =IF(F8=1,1,0) | I8: Matriz RF3 vincula alquiler sin sesion con Back End. Product Backlog S2/S3 cita RF3 literal; S3 lo marca Terminado.
A9: ART-B-REQ | B9: RNF2 | C9: Modificacion de datos de cuenta del cliente | D9: Textual | F9: 1 | G9: Sí | H9: =IF(F9=1,1,0) | I9: Matriz RNF2 vincula modificacion de datos de cuenta con Back End. Product Backlog S1/S2/S3 cita RNF2 literal y lo marca Terminado.
A10: ART-B-REQ | B10: RNF3 | C10: Seguridad percibida durante el proceso del alquiler | D10: Textual | F10: 1 | G10: Sí | H10: =IF(F10=1,1,0) | I10: Matriz RNF3 vincula seguridad del proceso con Front End y satisfaccion. Product Backlog S3 cita RNF3 literal y lo marca Terminado.
A11: ART-B-REQ | B11: RNF4 | C11: Página escrita en español | D11: Textual | F11: 1 | G11: Sí | H11: =IF(F11=1,1,0) | I11: Matriz RNF4 vincula idioma español con Front End/Back End. Product Backlog S1/S2/S3 cita RNF4 literal y lo marca Terminado.
A12: ART-B-REQ | B12: RF4 | C12: Identificación/login por correo y contraseña | D12: Textual | F12: 1 | G12: Sí | H12: =IF(F12=1,1,0) | I12: Matriz RF4 vincula login por correo/contraseña con Front End/Back End. Product Backlog S1/S2/S3 cita RF4 literal y lo marca Terminado.
A13: ART-B-REQ | B13: RF5 | C13: Acceso al tiempo restante de alquiler | D13: Textual | F13: 1 | G13: Sí | H13: =IF(F13=1,1,0) | I13: Matriz RF5 vincula tiempo restante de alquiler con Front End. Product Backlog S3 cita RF5 literal y lo marca Terminado.
A14: ART-B-REQ | B14: RF6 | C14: Barcos no disponibles claramente marcados | D14: Textual | F14: 1 | G14: Sí | H14: =IF(F14=1,1,0) | I14: Matriz RF6 vincula disponibilidad visible con Front End. Product Backlog S1/S2/S3 cita RF6 literal y lo marca Terminado.
A15: ART-B-REQ | B15: RNF5 | C15: Datos del barco: capacidad, imagen, categoria, fabricante y puerto | D15: Textual | F15: 1 | G15: Sí | H15: =IF(F15=1,1,0) | I15: Matriz RNF5 vincula datos del barco con Back End. Product Backlog S1/S2/S3 cita RNF5 literal y lo marca Terminado.
A16: ART-B-REQ | B16: RF7 | C16: Codigo de seguimiento asociado al alquiler, enviado por correo | D16: Textual | F16: 1 | G16: Sí | H16: =IF(F16=1,1,0) | I16: Matriz RF7 vincula codigo/correo de alquiler con Back End. Product Backlog S2/S3 cita RF7 y S3 lo marca Terminado.
... A21: ART-B-REQ | B21: RF12 | C21: Solicitud de datos de pago | D21: Textual | F21: 1 | G21: Sí | H21: =IF(F21=1,1,0) | I21: Matriz RF12 vincula datos de pago con Front End/Back End. Product Backlog S3 cita RF12 y lo marca Terminado.
A22: ART-B-REQ | B22: RF13 | C22: Estados del alquiler y pago posterior | D22: Textual | F22: 1 | G22: Sí | H22: =IF(F22=1,1,0) | I22: Matriz RF13 define PAGADO/PENDIENTE. Registro y Product Backlog S3 actualizan como RF13b con PAGADO, PENDIENTE DE PAGO, EN USO y DEVUELTO; S3 lo marca Terminado. | J22: ID evolucionado RF13 -> RF13b; trazable por funcion.
A23: ART-B-REQ | B23: RF14 | C23: Terminado proceso se envia un correo con datos de barco/puerto/importe | D23: Textual | F23: 1 | G23: Sí | H23: =IF(F23=1,1,0) | I23: Matriz RF14 vincula correo de finalizacion. Product Backlog S2/S3 cita RF14 y lo marca Terminado.
A24: ART-B-REQ | B24: RF15 | C24: Recordatorio de pago un dia antes del inicio de la reserva | D24: Textual | F24: 0 | G24: Sí | H24: =IF(F24=1,1,0) | I24: Matriz RF15 y Product Backlog S1/S2 lo incluyen como Won't. Sprint 3 Planning menciona RF15 en seguimiento de pedidos, pero Product Backlog S3 no conserva RF15 ni lo marca Terminado. | J24: Propuesto NO trazable: no queda evidencia de materializacion aguas abajo en backlog final.
A25: ART-B-REQ | B25: RF16 | C25: No devolucion de productos/alquileres | D25: Textual | F25: 1 | G25: Sí | H25: =IF(F25=1,1,0) | I25: Matriz RF16 vincula no devoluci?n con Front End/Back End. Product Backlog S1/S2/S3 cita RF16 no devolucion y lo marca Terminado.
A26: ART-B-REQ | B26: RNF6 | C26: Marca corporativa y politicas visibles | D26: Textual | F26: 1 | G26: Sí | H26: =IF(F26=1,1,0) | I26: Matriz RNF6 vincula marca/politicas con Front End. Product Backlog S1/S2/S3 cita RNF6 y lo marca Terminado.
A27: ART-B-REQ | B27: RO1 | C27: Manuales de usuario e instrucciones de puesta en produccion | D27: Textual | F27: 1 | G27: Sí | H27: =IF(F27=1,1,0) | I27: Matriz RO1 vincula documentacion final. Sprint 3 Planning incluye redactar manual e instrucciones de despliegue; Product Backlog S3 cita RO1 y lo marca Terminado.
A28: ART-B-REQ | B28: RO2 | C28: Uso de ciclo de vida hibrido | D28: Textual | F28: 1 | G28: Sí | H28: =IF(F28=1,1,0) | I28: Matriz RO2 vincula ciclo de vida hibrido con documentacion. Product Backlog S2/S3 cita RO2 y lo marca Terminado.
A29: ART-B-REQ | B29: RO3 | C29: Uso de plantillas proporcionadas por la organizacion | D29: Textual | F29: 1 | G29: Sí | H29: =IF(F29=1,1,0) | I29: Matriz RO3 vincula plantillas con documentacion. Product Backlog S2/S3 cita RO3 y lo marca Terminado.
A30: ART-B-REQ | B30: RF17 | C30: Usuarios registrados pueden ser clientes o administradores | D30: Textual | F30: 1 | G30: Sí | H30: =IF(F30=1,1,0) | I30: Matriz RF17 define roles cliente/administrador. Registro/Product Backlog usan la misma funcion con numeracion desplazada (RF16 en backlog), marcada Terminado. | J30: Trazable por funcion aunque hay desplazamiento de ID respecto a Registro/Backlog.
A31: ART-B-REQ | B31: RF18 | C31: Cliente ve productos y solo sus alquileres | D31: Textual | F31: 1 | G31: Sí | H31: =IF(F31=1,1,0) | I31: Matriz RF18 define visibilidad del cliente. Product Backlog S3 cita RF17 con la misma funci?n y lo marca Terminado. | J31: Trazable por funcion aunque hay desplazamiento de ID.
A32: ART-B-REQ | B32: RF19 | C32: Administrador ve/edita productos y revisa todos los alquileres | D32: Textual | F32: 1 | G32: Sí | H32: =IF(F32=1,1,0) | I32: Matriz RF19 define permisos de administrador. Registro/Product Backlog S3 contienen la misma funcion como RF18 y la marcan Terminado. | J32: Duda: ID RF19 no aparece en Registro/Backlog; propuesta trazable por coincidencia textual funcional segun 4.2.3.
A33: ART-B-PLAN | B33: PLAN-01/RF1 | C33: Catalogo/listado visible de barcos | D33: Textual | E33: 1 | F33: 1 | G33: No | H33: =IF(AND(E33=1,F33=1),1,0) | I33: Aguas arriba: Registro/Matriz RF1. Aguas abajo: Product Backlog S3 RF1 Terminado; 02_ARQUITECTURA.md documenta app store con listado y detalle; 03_MODELO_DE_DATOS.md documenta Product.
A34: ART-B-PLAN | B34: PLAN-02/RNF1 | C34: Mecanismo para modificar tiempo/duracion de alquiler | D34: Textual | E34: 1 | F34: 1 | G34: No | H34: =IF(AND(E34=1,F34=1),1,0) | I34: Aguas arriba: Registro/Matriz RNF1. Aguas abajo: Product Backlog S3 RNF1 Terminado; 02_ARQUITECTURA.md documenta carts con CartItem y fechas; 03_MODELO_DE_DATOS.md documenta CartItem y OrderProduct con fechas de reserva.
A35: ART-B-PLAN | B35: PLAN-03/RF2 | C35: Categorias de barcos ofertadas | D35: Textual | E35: 1 | F35: 1 | G35: No | H35: =IF(AND(E35=1,F35=1),1,0) | I35: Aguas arriba: Registro/Matriz RF2. Aguas abajo: Product Backlog S3 RF2 Terminado; 02_ARQUITECTURA.md documenta app category y store; 03_MODELO_DE_DATOS.md documenta Category y ForeignKey Product->Category.
A36: ART-B-PLAN | B36: PLAN-04/RNF2 | C36: Modificacion de datos de cuenta del cliente | D36: Textual | E36: 1 | F36: 1 | G36: No | H36: =IF(AND(E36=1,F36=1),1,0) | I36: Aguas arriba: Registro/Matriz RNF2. Aguas abajo: Product Backlog S3 RNF2 Terminado; 02_ARQUITECTURA.md documenta accounts/views.py con dashboard/perfil y forms UserForm/UserProfileForm; 03_MODELO_DE_DATOS.md documenta UserProfile.
A37: ART-B-PLAN | B37: PLAN-05/RNF4 | C37: Interfaz en español | D37: Textual | E37: 1 | F37: 1 | G37: No | H37: =IF(AND(E37=1,F37=1),1,0) | I37: Aguas arriba: Registro/Matriz RNF4. Aguas abajo: Product Backlog S3 RNF4 Terminado; evidencia textual en plantillas y documentos del producto auditado, con templates globales descritos en 02_ARQUITECTURA.md.
A38: ART-B-PLAN | B38: PLAN-06/RF4 | C38: Login por correo y clave | D38: Textual | E38: 1 | F38: 1 | G38: No | H38: =IF(AND(E38=1,F38=1),1,0) | I38: Aguas arriba: Registro/Matriz RF4. Aguas abajo: Product Backlog S3 RF4 Terminado; 02_ARQUITECTURA.md documenta accounts con Register/login/logout; 03_MODELO_DE_DATOS.md documenta Account con USERNAME_FIELD=email.
A39: ART-B-PLAN | B39: PLAN-07/RF6 | C39: Marcado de barcos no disponibles | D39: Textual | E39: 1 | F39: 1 | G39: No | H39: =IF(AND(E39=1,F39=1),1,0) | I39: Aguas arriba: Registro/Matriz RF6. Aguas abajo: Product Backlog S3 RF6 Terminado; 03_MODELO_DE_DATOS.md documenta Product.is_available y stock; 02_ARQUITECTURA.md documenta store como catalogo/disponibilidad.
A40: ART-B-PLAN | B40: PLAN-08/RNF5 | C40: Datos de barco: capacidad, imagen, categoria, fabricante y puerto | D40: Textual | E40: 1 | F40: 1 | G40: No | H40: =IF(AND(E40=1,F40=1),1,0) | I40: Aguas arriba: Registro/Matriz RNF5. Aguas abajo: Product Backlog S3 RNF5 Terminado; 03_MODELO_DE_DATOS.md documenta Product con images, category, fabricante, puerto y capacidad.
A41: ART-B-PLAN | B41: PLAN-09/RF8 | C41: Catalogo por categorias y filtros | D41: Textual | E41: 1 | F41: 1 | G41: No | H41: =IF(AND(E41=1,F41=1),1,0) | I41: Aguas arriba: Registro/Matriz RF8. Aguas abajo: Product Backlog S3 RF8 Terminado; 02_ARQUITECTURA.md documenta store como catalogo, filtros de busqueda y navegacion por categorias.
A42: ART-B-PLAN | B42: PLAN-10/RF16a | C42: No devolucion de productos/alquileres | D42: Textual | E42: 1 | F42: 1 | G42: No | H42: =IF(AND(E42=1,F42=1),1,0) | I42: Aguas arriba: Registro/Matriz RF16. Aguas abajo: Product Backlog S3 mantiene RF16 Terminado; 03_MODELO_DE_DATOS.md documenta estados/ordenes y RNF8 cubre aviso de no devolucion asociado a cancelacion. | J42: Trazabilidad funcional, no por modulo aislado.
A43: ART-B-PLAN | B43: PLAN-11/RNF6 | C43: Marca corporativa y politicas visibles | D43: Textual | E43: 1 | F43: 0 | G43: No | H43: =IF(AND(E43=1,F43=1),1,0) | I43: Aguas arriba: Registro/Matriz RNF6. Aguas abajo: Product Backlog S3 lo marca Terminado, pero en la auditoria tecnica no hay evidencia especifica de politicas/brand content mas alla de plantillas estaticas genericas. | J43: Propuesto NO trazable: falta evidencia aguas abajo especifica.
A44: ART-B-PLAN | B44: PLAN-12/RF10 | C44: Solicitud de datos de usuario en el alquiler | D44: Textual | E44: 1 | F44: 1 | G44: No | H44: =IF(AND(E44=1,F44=1),1,0) | I44: Aguas arriba: Registro/Matriz RF10. Aguas abajo: Product Backlog S3 RF10 Terminado; 02_ARQUITECTURA.md documenta orders/forms.py OrderForm y templates de checkout; 03_MODELO_DE_DATOS.md documenta Order con datos asociados.
A45: ART-B-PLAN | B45: PLAN-13/RF11 | C45: Solicitud de datos de envio: hora, dia, puerto | D45: Textual | E45: 1 | F45: 1 | G45: No | H45: =IF(AND(E45=1,F45=1),1,0) | I45: Aguas arriba: Registro/Matriz RF11. Aguas abajo: Product Backlog S3 RF11 Terminado; 03_MODELO_DE_DATOS.md documenta Product.puerto y OrderProduct con fechas de reserva; 02_ARQUITECTURA.md documenta checkout en orders.
A46: ART-B-PLAN | B46: PLAN-14/RF12 | C46: Solicitud de datos de pago | D46: Textual | E46: 1 | F46: 1 | G46: No | H46: =IF(AND(E46=1,F46=1),1,0) | I46: Aguas arriba: Registro/Matriz RF12. Aguas abajo: Product Backlog S3 RF12 Terminado; 02_ARQUITECTURA.md documenta orders/views.py payments y PayPal/contra-reembolso; 03_MODELO_DE_DATOS.md documenta Payment.
A47: ART-B-PLAN | B47: PLAN-15/RF13b | C47: Estados de alquiler y pago posterior | D47: Textual | E47: 1 | F47: 1 | G47: No | H47: =IF(AND(E47=1,F47=1),1,0) | I47: Aguas arriba: Registro RF13b/Matriz RF13. Aguas abajo: Product Backlog S3 RF13b Terminado; 02_ARQUITECTURA.md documenta orders con mark_pending y CRUD admin; 03_MODELO_DE_DATOS.md documenta Order/Payment. | J47: ID evolucionado RF13 -> RF13b; trazabilidad por funcion.
A48: ART-B-PLAN | B48: PLAN-16/RF14 | C48: Correo al completar alquiler | D48: Textual | E48: 1 | F48: 1 | G48: No | H48: =IF(AND(E48=1,F48=1),1,0) | I48: Aguas arriba: Registro/Matriz RF14. Aguas abajo: Product Backlog S3 RF14 Terminado; 02_ARQUITECTURA.md documenta orders/views.py order_complete y configuracion email en ecommerce/settings.py.
A49: ART-B-PLAN | B49: PLAN-17/RF9 | C49: Añadir a cesta y completar alquiler | D49: Textual | E49: 1 | F49: 1 | G49: No | H49: =IF(AND(E49=1,F49=1),1,0) | I49: Aguas arriba: Registro/Matriz RF9. Aguas abajo: Product Backlog S3 RF9 Terminado; 02_ARQUITECTURA.md documenta carts views add_cart/cart/checkout; 03_MODELO_DE_DATOS.md documenta Cart y CartItem.
A50: ART-B-PLAN | B50: PLAN-18/RP1 | C50: Versiones para pruebas disponibles en PaaS | D50: Textual | E50: 1 | F50: 1 | G50: No | H50: =IF(AND(E50=1,F50=1),1,0) | I50: Aguas arriba: Registro/Matriz RP1. Aguas abajo: Product Backlog S3 RP1 Terminado; Sprint 1 Planning decide usar Render; 02_ARQUITECTURA.md documenta Dockerfile y docker-compose.yml como soporte de despliegue.
A51: ART-B-PLAN | B51: PLAN-19/RO1 | C51: Manual de usuario e instrucciones de puesta en produccion | D51: Textual | E51: 1 | F51: 1 | G51: No | H51: =IF(AND(E51=1,F51=1),1,0) | I51: Aguas arriba: Registro/Matriz RO1. Aguas abajo: Sprint 3 Planning planifica manual/despliegue y Product Backlog S3 RO1 Terminado; Informe de cierre lista informes finales generados. | J51: Trazabilidad documental, no de codigo.
A52: ART-B-PLAN | B52: PLAN-20/RO2 | C52: Uso de ciclo de vida hibrido | D52: Textual | E52: 1 | F52: 0 | G52: No | H52: =IF(AND(E52=1,F52=1),1,0) | I52: Aguas arriba: Registro/Matriz RO2. Aguas abajo: Product Backlog S3 lo marca Terminado, pero no hay artefacto tecnico o entregable especifico en la evidencia baseline que materialice el ciclo hibrido como item verificable. | J52: Propuesto NO trazable: evidencia de proceso insuficiente como entregable aguas abajo.
A53: ART-B-PLAN | B53: PLAN-21/RO3 | C53: Uso de plantillas de la organizacion | D53: Textual | E53: 1 | F53: 0 | G53: No | H53: =IF(AND(E53=1,F53=1),1,0) | I53: Aguas arriba: Registro/Matriz RO3. Aguas abajo: Product Backlog S3 lo marca Terminado, pero no hay evidencia especifica que permita verificar que plantilla se aplica como entregable. | J53: Propuesto NO trazable: falta evidencia aguas abajo especifica.
A54: ART-B-PLAN | B54: PLAN-22/RF16b | C54: Usuarios registrados pueden ser clientes o administradores | D54: Textual | E54: 1 | F54: 1 | G54: No | H54: =IF(AND(E54=1,F54=1),1,0) | I54: Aguas arriba: Registro contiene la funcion como RF16 y Matriz como RF17. Aguas abajo: Product Backlog S3 RF16 Terminado; 03_MODELO_DE_DATOS.md documenta Account con is_admin/is_staff/is_superadmin. | J54: ID desplazado entre Registro/Matriz; trazable por funcion.
A55: ART-B-PLAN | B55: PLAN-23/RF17 | C55: Cliente ve productos y unicamente sus alquileres | D55: Textual | E55: 1 | F55: 1 | G55: No | H55: =IF(AND(E55=1,F55=1),1,0) | I55: Aguas arriba: Registro RF17/Matriz RF18. Aguas abajo: Product Backlog S3 RF17 Terminado; 02_ARQUITECTURA.md documenta store y orders con historial de reservas; 03_MODELO_DE_DATOS.md documenta Order ligado a Account.
A56: ART-B-PLAN | B56: PLAN-24/RF18 | C56: Administrador ve/edita productos y revisa todos los alquileres | D56: Textual | E56: 1 | F56: 1 | G56: No | H56: =IF(AND(E56=1,F56=1),1,0) | I56: Aguas arriba: Registro RF18/Matriz RF19. Aguas abajo: Product Backlog S3 RF18 Terminado; 02_ARQUITECTURA.md documenta CRUD admin de barcos, lista de usuarios y reservas; 03_MODELO_DE_DATOS.md documenta admin/Account/Order.
A57: ART-B-PLAN | B57: PLAN-25/RNF8 | C57: Aviso de no devolucion de importe/fianza al cancelar | D57: Textual | E57: 1 | F57: 1 | G57: No | H57: =IF(AND(E57=1,F57=1),1,0) | I57: Aguas arriba: Registro/Matriz RNF8. Aguas abajo: Product Backlog S3 RNF8 Terminado; Informe de cierre y modelo de pedidos/pagos documentan gestion de pagos, estados e incidencias asociadas a fianza/devolucion. | J57: Trazabilidad funcional indirecta; suficiente por coincidencia con pago/cancelacion.
A58: ART-B-PLAN | B58: PLAN-26/RNF9 | C58: Tasa de combustible y excepcion para velero | D58: Textual | E58: 1 | F58: 1 | G58: No | H58: =IF(AND(E58=1,F58=1),1,0) | I58: Aguas arriba: Registro/Matriz RNF9. Aguas abajo: Product Backlog S3 RNF9 Terminado; funcion vinculada al calculo de reserva/pedido en orders/carts y precios por dia documentados en 03_MODELO_DE_DATOS.md. | J58: Trazabilidad por funcion de negocio; no aparece como campo aislado.
A59: ART-B-PLAN | B59: PLAN-27/RF3 | C59: Reserva sin inicio de sesion obligatorio | D59: Textual | E59: 1 | F59: 1 | G59: No | H59: =IF(AND(E59=1,F59=1),1,0) | I59: Aguas arriba: Registro/Matriz RF3. Aguas abajo: Product Backlog S3 RF3 Terminado; 02_ARQUITECTURA.md documenta carts/checkout y orders como flujo de reserva; requisito se conserva en backlog final.
A60: ART-B-PLAN | B60: PLAN-28/RNF3 | C60: Seguridad percibida durante el alquiler | D60: Textual | E60: 1 | F60: 1 | G60: No | H60: =IF(AND(E60=1,F60=1),1,0) | I60: Aguas arriba: Registro/Matriz RNF3. Aguas abajo: Product Backlog S3 RNF3 Terminado; 02_ARQUITECTURA.md documenta autenticacion accounts y proceso de checkout/pagos. | J60: Trazabilidad funcional indirecta por autenticacion/checkout.
A61: ART-B-PLAN | B61: PLAN-29/RF5 | C61: Acceso al tiempo restante de alquiler | D61: Textual | E61: 1 | F61: 1 | G61: No | H61: =IF(AND(E61=1,F61=1),1,0) | I61: Aguas arriba: Registro/Matriz RF5. Aguas abajo: Product Backlog S3 RF5 Terminado; 03_MODELO_DE_DATOS.md documenta OrderProduct con fechas de reserva y Order con seguimiento.
A62: ART-B-PLAN | B62: PLAN-30/RF7 | C62: Código de seguimiento asociado al alquiler | D62: Textual | E62: 1 | F62: 1 | G62: No | H62: =IF(AND(E62=1,F62=1),1,0) | I62: Aguas arriba: Registro/Matriz RF7. Aguas abajo: Product Backlog S3 RF7 Terminado; 03_MODELO_DE_DATOS.md documenta Order.order_note reutilizado para codigo RES-XXXX de seguimiento.
A63: ART-B-DIS | B63: DIS-01 | C63: Arquitectura/apps Django principales (accounts, category, store, carts, orders) | D63: Textual | E63: 1 | F63: 1 | G63: No | H63: =IF(AND(E63=1,F63=1),1,0) | I63: Aguas arriba: RF1/RF2/RF3/RF12/RF13b/RF16-RF18 justifican catologo, alquiler/reserva, pagos y roles. Aguas abajo: 02_ARQUITECTURA.md enumera apps, accounts, category, store, carts y orders con models.py, views.py, urls.py y admin.py. | J63: Baseline reconstruido ex post; se aplica lectura inversa declarada en 4.3.3: lo construido queda documentado por la auditoria tecnica.
A64: ART-B-DIS | B64: DIS-02 | C64: Modelo de datos principal del sistema (usuarios, cat?logo/barcos, carrito/reserva, pagos/pedidos) | D64: Textual | E64: 1 | F64: 1 | G64: No | H64: =IF(AND(E64=1,F64=1),1,0) | I64: Aguas arriba: RF/RNF sobre usuarios, barcos/categorias, proceso de alquiler, datos de pago y estados del alquiler. Aguas abajo: 03_MODELO_DE_DATOS.md documenta Category, Account/UserProfile, Product/Puerto/Fabricante, Cart/CartItem, Payment/Order/OrderProduct. | J64: Caso claro: los modelos auditados materializan las funciones nucleares del registro de requisitos.
A65: ART-B-SEG-S1 | B65: SEG-S1-01 | C65: Cumplimiento de issues funcionales planificados en Sprint 1 (reserva, catologo/filtros, usuarios/roles, CRUD barcos) | D65: Textual | E65: 1 | F65: 1 | G65: No | H65: =IF(AND(E65=1,F65=1),1,0) | I65: Aguas arriba: Sprint 1 - Planning.pdf lista issues 1-4: reserva de barco, catologo/filtro, usuarios con roles y CRUD de barcos. Aguas abajo: Sprint 1 - Review.pdf declara que todas las tareas planificadas para el Sprint 1 fueron completadas; Product Backlog S1 marca Terminado en RF1/RNF1/RF2/RNF2/RNF4/RF4/RF6/RNF5/RF8/RF16/RNF6. | J65: Caso claro; seguimiento narrativo normalizado a item agregado por N=2 cerrado en la planilla.
A66: ART-B-SEG-S1 | B66: SEG-S1-02 | C66: Continuidad del Sprint 1 hacia Sprint 2 tras cierre completo de tareas | D66: Textual | E66: 1 | F66: 1 | G66: No | H66: =IF(AND(E66=1,F66=1),1,0) | I66: Aguas arriba: Sprint 1 - Planning.pdf fija el primer bloque de trabajo y decisiones tecnicas de coordinacion/despliegue. Aguas abajo: Sprint 1 - Review.pdf indica que Sprint 2 continua con la planificaciin realizada porque todas las tareas del Sprint 1 se completaron. | J66: Caso claro; el enlace aguas abajo es cierre de review y continuidad explicita, no commit individual.
A67: ART-B-SEG-S2 | B67: SEG-S2-01 | C67: Cumplimiento parcial/verificado de tareas del Sprint 2 (despliegue, admin y funciones de alquiler ya terminadas en backlog) | D67: Textual | E67: 1 | F67: 1 | G67: No | H67: =IF(AND(E67=1,F67=1),1,0) | I67: Aguas arriba: Sprint 2 - Planning.pdf define issues 5-8: pagos online, pagos contra reembolso, despliegue y módulo administrador. Aguas abajo: Sprint 2 - Product Backlog.pdf marca Terminado en RF10, RF11, RF13, RF14, RF9, RP1, RO2, RO3, RF16, RF18, RNF9, RF3 y RF7; Sprint 2 - Review.pdf confirma que todas las tareas salvo pagos y seguimiento se completaron. | J67: Caso claro: el review distingue explicitamente completado vs pendiente, por lo que el seguimiento es auditable.
A68: ART-B-SEG-S2 | B68: SEG-S2-02 | C68: Arrastre controlado de sistema de pagos y seguimiento de pedidos hacia Sprint 3 | D68: Textual | E68: 1 | F68: 1 | G68: No | H68: =IF(AND(E68=1,F68=1),1,0) | I68: Aguas arriba: Sprint 2 - Planning.pdf incluye sistema de pagos online, pago contra reembolso y despliegue/admin. Aguas abajo: Sprint 2 - Review.pdf declara que pagos y seguimiento de pedidos no se completaron y que se completaran en Sprint 3; Sprint 3 - Planning.pdf los recoge como tareas continuadas. | J68: Caso claro: no es fallo de trazabilidad, sino continuidad documentada hacia el sprint siguiente.
A69: ART-B-SEG-S3 | B69: SEG-S3-01 | C69: Cierre de tareas continuadas del Sprint 3: pagos, seguimiento, pruebas y manual/despliegue | D69: Textual | E69: 1 | F69: 1 | G69: No | H69: =IF(AND(E69=1,F69=1),1,0) | I69: Aguas arriba: Sprint 3 - Planning.pdf lista pagos (RF13/RF12/RF11/RF9/RNF7/RNF8/RNF9), seguimiento de pedidos (RF14/RF15), pruebas finales y manual/despliegue (RO1). Aguas abajo: Sprint 3 - Product Backlog.pdf marca Terminado en RF12, RF13b, RF14, RO1, RF17, RNF8, RNF9, RF5 y RF7; Sprint 3 - Review.pdf declara completadas todas las tareas planificadas. | J69: Caso claro; recoge explicitamente las tareas arrastradas del Sprint 2.
A70: ART-B-SEG-S3 | B70: SEG-S3-02 | C70: Paso a cierre del proyecto con tareas del Sprint 3 completadas | D70: Textual | E70: 1 | F70: 1 | G70: No | H70: =IF(AND(E70=1,F70=1),1,0) | I70: Aguas arriba: Sprint 3 - Planning.pdf define el bloque final de implementacion y validacion. Aguas abajo: Sprint 3 - Review.pdf indica que todas las tareas planificadas para Sprint 3 se completaron y que el cierre continua de acuerdo con la planificacion realizada. | J70: Caso claro; enlace de cierre documentado por el review del sprint.
A71: ART-B-CIE | B71: CIE-01 | C71: Leccion sobre definicion inicial de requisitos, alcance y cronograma | D71: Textual | E71: 1 | F71: 1 | G71: Sí | H71: =IF(E71=1,1,0) | I71: Aguas arriba: Lecciones aprendidas.pdf describe problemas significativos en definicion de requisitos iniciales, desviaciones de alcance/cronograma, retrasos y cambios no previstos. Aguas abajo/recomendacion: propone mejorar la gestion de requisitos y la definicion inicial del alcance mediante uso mas efectivo de herramientas agiles para priorizar tareas. | J71: Caso claro; cierre como extremo de cadena, se exige evidencia aguas arriba y se conserva tambien la recomendacion cuando aplica.
A72: ART-B-CIE | B72: CIE-02 | C72: Desviacion de pasarela de pago: Stripe planificado, PayPal aceptado | D72: Textual | E72: 1 | F72: 1 | G72: Sí | H72: =IF(E72=1,1,0) | I72: Aguas arriba: Sprint 2 - Planning.pdf planifica Stripe; Sprint 2 - Review.pdf indica que pagos quedan pendientes; Sprint 3 - Planning.pdf decide usar PayPal. Informe de cierre.pdf registra entregable planificado Stripe y entregable aceptado PayPal por error de Stripe y mayor sencillez de PayPal. | J72: Caso claro; el ajuste final queda formalizado en informe de cierre.

Sheet 02_R1_sintesis_artefactos
A1: R1 — Síntesis complementaria por artefacto (M1 oficial + M3/M4/M5)
A2: INSTRUCCIONES: Esta hoja resume la evaluación por artefacto. M1 nivel oficial se toma de 03b_R1_M1_resumen; la justificación M1 se conserva como explicación cualitativa. M3, M4 y M5 se registran aquí con sus evidencias y cálculos. Nota M1: la fuente oficial de completitud es 03_R1_M1_checklist + 03b_R1_M1_resumen. Esta hoja no recalcula M1; lo referencia para integrar todas las métricas por artefacto.
A4: ID artefacto | B4: Caso | C4: Run | D4: Familia | E4: Artefacto | F4: M1 (desde 03b) | G4: M1 justificación (complementaria) | H4: M3 nivel (0-3) | I4: M3 (# contradicciones) | J4: M3 justificación | K4: M4 (N total ítems) | L4: M4 (N ítems trazables) | M4: M4 % calculado | N4: M4 tramo | O4: M4 justificación | P4: M5 G1 | Q4: M5 G2 | R4: M5 G3 | S4: M5 G4 | T4: M5 Nivel (0-4)
A5: ART-B-REQ | B5: Baseline | C5: — | D5: Requisitos | E5: Registro Requisitos + Matriz Trazabilidad | F5: =IFERROR(INDEX('03b_R1_M1_resumen'!$I:$I,MATCH(A5,'03b_R1_M1_resumen'!$A:$A,0)),"") | G5: Registro y matriz contienen RF/RNF con ID, categoria, prioridad, criterio de aceptacion, interesado y trazabilidad basica; cobertura sustancial/completa de requisitos de alquiler, catalogo, reserva, pagos y administracion. | H5: 1 | I5: 3 | J5: Hay inconsistencias de identificacion entre Registro y Matriz: RF13/RF15/RF19 no aparecen igual en ambos documentos y el Registro salta numeracion tras RF16. No se detecta contradiccion funcional mayor. | K5: 28 | L5: 27 | M5: =IF(AND(K5>0,L5<>""),L5/K5*100,"") | N5: =IF(M5="","",IF(M5<25,"0-25 ausente/residual",IF(M5<50,"25-50 parcial",IF(M5<75,"50-75 sustancial","75-100 alta")))) | O5: Matriz incluye fuente/interesado, objetivo, entregable y criterio para la mayoria de requisitos; RF19 queda sin correspondencia clara en Registro/backlogs. | P5: 1 | Q5: 1 | R5: 1 | S5: 0 | T5: =SUM(P5:S5)
A6: ART-B-PLAN | B6: Baseline | C6: — | D6: Planificación | E6: Sprint Plannings + Product Backlogs S1-S2-S3 | F6: =IFERROR(INDEX('03b_R1_M1_resumen'!$I:$I,MATCH(A6,'03b_R1_M1_resumen'!$A:$A,0)),"") | G6: Sprint Plannings y Product Backlogs existen para los tres sprints, con issues/requisitos, estado y responsables. Falta granularidad de HU, criterios de aceptacion por historia y dependencias explicitas. | H6: 2 | I6: 2 | J6: Fallos menores: algunos documentos mantienen tipo documental incorrecto y hay cambios de pasarela/despliegue entre sprints, aunque quedan parcialmente justificados en planning/cierre. | K6: 30 | L6: 27 | M6: =IF(AND(K6>0,L6<>""),L6/K6*100,"") | N6: =IF(M6="","",IF(M6<25,"0-25 ausente/residual",IF(M6<50,"25-50 parcial",IF(M6<75,"50-75 sustancial","75-100 alta")))) | O6: Los Product Backlogs contienen 30 items trazados por ID a requisitos/sprints; algunos IDs no tienen correspondencia uniforme en Registro/Matriz. | P6: 1 | Q6: 1 | R6: 1 | S6: 0 | T6: =SUM(P6:S6)
A7: ART-B-DIS | B7: Baseline | C7: — | D7: Diseño técnico | E7: Auditoría posthoc 02_ARQUITECTURA + 03_MODELO_DATOS | F7: =IFERROR(INDEX('03b_R1_M1_resumen'!$I:$I,MATCH(A7,'03b_R1_M1_resumen'!$A:$A,0)),"") | G7: Los documentos posthoc 02_ARQUITECTURA y 03_MODELO_DE_DATOS describen stack, estructura, componentes y modelo de datos con suficiente cobertura tecnica del producto. | H7: 3 | I7: 0 | J7: No se observan contradicciones internas relevantes entre arquitectura y modelo de datos en la documentacion disponible. | K7: 2 | L7: 2 | M7: =IF(AND(K7>0,L7<>""),L7/K7*100,"") | N7: =IF(M7="","",IF(M7<25,"0-25 ausente/residual",IF(M7<50,"25-50 parcial",IF(M7<75,"50-75 sustancial","75-100 alta")))) | O7: Trazabilidad inferida por los dos documentos tecnicos: arquitectura y modelo de datos cubren componentes principales del sistema entregado. | P7: 0 | Q7: 0 | R7: 0 | S7: 0 | T7: =SUM(P7:S7)
A8: ART-B-SEG-S1 | B8: Baseline | C8: — | D8: Seguimiento | E8: Sprint Review 1 + Retrospective 1 | F8: =IFERROR(INDEX('03b_R1_M1_resumen'!$I:$I,MATCH(A8,'03b_R1_M1_resumen'!$A:$A,0)),"") | G8: Review y Retrospective del Sprint 1 existen, con acta, revision de tareas y acciones de mejora; el detalle de evidencias, metricas y aceptacion es limitado. | H8: 2 | I8: 1 | J8: Fallo menor documental: algunos encabezados identifican la review/retrospective como Sprint Planning. No afecta al contenido central. | K8: 2 | L8: 2 | M8: =IF(AND(K8>0,L8<>""),L8/K8*100,"") | N8: =IF(M8="","",IF(M8<25,"0-25 ausente/residual",IF(M8<50,"25-50 parcial",IF(M8<75,"50-75 sustancial","75-100 alta")))) | O8: Review y retrospectiva enlazan con el cierre del Sprint 1 y con las tareas planificadas, aunque sin trazabilidad itemizada. | P8: 1 | Q8: 0 | R8: 0 | S8: 1 | T8: =SUM(P8:S8)
A9: ART-B-SEG-S2 | B9: Baseline | C9: — | D9: Seguimiento | E9: Sprint Review 2 + Retrospective 2 | F9: =IFERROR(INDEX('03b_R1_M1_resumen'!$I:$I,MATCH(A9,'03b_R1_M1_resumen'!$A:$A,0)),"") | G9: Review y Retrospective del Sprint 2 existen e incluyen tareas no completadas, desviacion de horas y conflicto entre ramas; falta detalle itemizado de aceptacion. | H9: 2 | I9: 1 | J9: Fallo menor de consistencia documental por encabezado/tipo de documento; el contenido de seguimiento es coherente. | K9: 2 | L9: 2 | M9: =IF(AND(K9>0,L9<>""),L9/K9*100,"") | N9: =IF(M9="","",IF(M9<25,"0-25 ausente/residual",IF(M9<50,"25-50 parcial",IF(M9<75,"50-75 sustancial","75-100 alta")))) | O9: La review identifica tareas completadas/no completadas y la retrospectiva registra incidencia; trazabilidad suficiente a nivel de sprint. | P9: 1 | Q9: 1 | R9: 1 | S9: 1 | T9: =SUM(P9:S9)
A10: ART-B-SEG-S3 | B10: Baseline | C10: — | D10: Seguimiento | E10: Sprint Review 3 + Retrospective 3 | F10: =IFERROR(INDEX('03b_R1_M1_resumen'!$I:$I,MATCH(A10,'03b_R1_M1_resumen'!$A:$A,0)),"") | G10: Review y Retrospective del Sprint 3 existen y documentan cierre de tareas, desviaciones y aprendizajes; la evidencia sigue siendo resumida. | H10: 1 | I10: 2 | J10: Contradiccion factual menor de fechas en la retrospectiva del Sprint 3 frente a planning/review, y persistencia de encabezados no alineados. | K10: 2 | L10: 2 | M10: =IF(AND(K10>0,L10<>""),L10/K10*100,"") | N10: =IF(M10="","",IF(M10<25,"0-25 ausente/residual",IF(M10<50,"25-50 parcial",IF(M10<75,"50-75 sustancial","75-100 alta")))) | O10: La documentacion enlaza el Sprint 3 con tareas continuadas de pagos/seguimiento y cierre, sin matriz itemizada. | P10: 1 | Q10: 0 | R10: 1 | S10: 1 | T10: =SUM(P10:S10)
A11: ART-B-CIE | B11: Baseline | C11: — | D11: Cierre | E11: Lecciones Aprendidas + Informe de cierre | F11: =IFERROR(INDEX('03b_R1_M1_resumen'!$I:$I,MATCH(A11,'03b_R1_M1_resumen'!$A:$A,0)),"") | G11: Lecciones aprendidas e Informe de cierre existen y cubren desviaciones, costes, cronograma y recomendaciones, pero no incluyen aprobacion formal detallada ni trazabilidad exhaustiva. | H11: 3 | I11: 0 | J11: Los documentos de cierre son internamente coherentes: las desviaciones de pago, cronograma y costes se explican de forma consistente. | K11: 2 | L11: 2 | M11: =IF(AND(K11>0,L11<>""),L11/K11*100,"") | N11: =IF(M11="","",IF(M11<25,"0-25 ausente/residual",IF(M11<50,"25-50 parcial",IF(M11<75,"50-75 sustancial","75-100 alta")))) | O11: Informe de cierre y lecciones aprendidas enlazan con desviaciones, incidencias y recomendaciones finales del proyecto. | P11: 0 | Q11: 1 | R11: 1 | S11: 1 | T11: =SUM(P11:S11)
A12: ART-run_01-REQ | B12: Pipeline | C12: run_01 | D12: Requisitos | E12: registro_requisitos.json + .md | F12: =IFERROR(INDEX('03b_R1_M1_resumen'!$I:$I,MATCH(A12,'03b_R1_M1_resumen'!$A:$A,0)),"") | G12: registro_requisitos contiene 36 RF y 9 RNF con ID, descripcion y prioridad; cubre el alcance principal, aunque la prioridad es poco discriminante y algunos RNF estan agrupados. | H12: 2 | I12: 2 | J12: Gate 1 solo marca observaciones no bloqueantes: priorizacion poco informativa y granularidad limitada en seguridad/importe. | K12: 45 | L12: 45 | M12: =IF(AND(K12>0,L12<>""),L12/K12*100,"") | N12: =IF(M12="","",IF(M12<25,"0-25 ausente/residual",IF(M12<50,"25-50 parcial",IF(M12<75,"50-75 sustancial","75-100 alta")))) | O12: Todos los RF/RNF tienen correspondencia textual con el backlog generado y el gate acepta cobertura suficiente del brief. | P12: 1 | Q12: 0 | R12: 0 | S12: 1 | T12: =SUM(P12:S12)
A13: ART-run_01-PLAN | B13: Pipeline | C13: run_01 | D13: Planificación | E13: backlog + plan_sprints + riesgos | F13: =IFERROR(INDEX('03b_R1_M1_resumen'!$I:$I,MATCH(A13,'03b_R1_M1_resumen'!$A:$A,0)),"") | G13: backlog, plan_sprints y riesgos estan presentes; hay 21 HU, tres sprints y 10 riesgos. Falta enlace explicito requisito-HU en algunas historias. | H13: 2 | I13: 2 | J13: Gate 2 senala observaciones no bloqueantes sobre concentracion de complejidad, seed en Dockerfile y posible exceso con cron/Celery. | K13: 21 | L13: 21 | M13: =IF(AND(K13>0,L13<>""),L13/K13*100,"") | N13: =IF(M13="","",IF(M13<25,"0-25 ausente/residual",IF(M13<50,"25-50 parcial",IF(M13<75,"50-75 sustancial","75-100 alta")))) | O13: Las 21 HU aparecen planificadas en sprints y son trazables por contenido al registro de requisitos. | P13: 1 | Q13: 0 | R13: 0 | S13: 1 | T13: =SUM(P13:S13)
A14: ART-run_01-DIS | B14: Pipeline | C14: run_01 | D14: Diseño técnico | E14: diseno_tecnico.json + .md | F14: =IFERROR(INDEX('03b_R1_M1_resumen'!$I:$I,MATCH(A14,'03b_R1_M1_resumen'!$A:$A,0)),"") | G14: diseno_tecnico contiene stack, 6 apps Django, 8 modelos y 29 rutas; cubre el stack, la estructura de apps, el modelo de datos y las rutas necesarias para generar el producto. Gate 3 lo acepta con observaciones no bloqueantes. | H14: 2 | I14: 3 | J14: Gate 3 marca observaciones menores: ImageField declarado como cadena, posible confusi?n core/settings frente al paquete del proyecto, disponibilidad por fechas no derivada solo de Barco.disponible y logout GET preferible como POST. | K14: 37 | L14: 36 | M14: =IF(AND(K14>0,L14<>""),L14/K14*100,"") | N14: =IF(M14="","",IF(M14<25,"0-25 ausente/residual",IF(M14<50,"25-50 parcial",IF(M14<75,"50-75 sustancial","75-100 alta")))) | O14: 36 de 37 elementos de apps/modelos/rutas enlazan textualmente con requisitos o backlog; queda al menos un detalle t?cnico menos trazado/documentado de forma expl?cita. | P14: 1 | Q14: 0 | R14: 0 | S14: 1 | T14: =SUM(P14:S14)
A15: ART-run_01-SEG-S1 | B15: Pipeline | C15: run_01 | D15: Seguimiento | E15: review_sprint_1.json + .md | F15: =IFERROR(INDEX('03b_R1_M1_resumen'!$I:$I,MATCH(A15,'03b_R1_M1_resumen'!$A:$A,0)),"") | G15: review_sprint_1 incluye backlog pedido, archivos entregados, cumplimiento, arranque, rutas, templates e incidencias. | H15: 3 | I15: 0 | J15: No se detectan contradicciones internas; las incidencias estan registradas como seguimiento, no como incoherencias del artefacto. | K15: 8 | L15: 8 | M15: =IF(AND(K15>0,L15<>""),L15/K15*100,"") | N15: =IF(M15="","",IF(M15<25,"0-25 ausente/residual",IF(M15<50,"25-50 parcial",IF(M15<75,"50-75 sustancial","75-100 alta")))) | O15: Los 8 items pedidos del sprint aparecen en la review con evidencias de cumplimiento/entrega. | P15: 1 | Q15: 0 | R15: 1 | S15: 1 | T15: =SUM(P15:S15)
A16: ART-run_01-SEG-S2 | B16: Pipeline | C16: run_01 | D16: Seguimiento | E16: review_sprint_2.json + .md | F16: =IFERROR(INDEX('03b_R1_M1_resumen'!$I:$I,MATCH(A16,'03b_R1_M1_resumen'!$A:$A,0)),"") | G16: review_sprint_2 documenta 6 items pedidos, entregables, cumplimiento, arranque, rutas y templates; no registra incidencias. | H16: 3 | I16: 0 | J16: Artefacto coherente, sin contradicciones internas detectadas. | K16: 6 | L16: 6 | M16: =IF(AND(K16>0,L16<>""),L16/K16*100,"") | N16: =IF(M16="","",IF(M16<25,"0-25 ausente/residual",IF(M16<50,"25-50 parcial",IF(M16<75,"50-75 sustancial","75-100 alta")))) | O16: Los 6 items pedidos quedan enlazados con entregables y checks de la review. | P16: 1 | Q16: 0 | R16: 0 | S16: 1 | T16: =SUM(P16:S16)
... A32: ART-run_03-CIE | B32: Pipeline | C32: run_03 | D32: Cierre | E32: lecciones_aprendidas.md + review_final.md + readme.md | F32: =IFERROR(INDEX('03b_R1_M1_resumen'!$I:$I,MATCH(A32,'03b_R1_M1_resumen'!$A:$A,0)),"") | G32: Cierre con lecciones_aprendidas, review_final y readme; review_final muestra OK global y 16 checks ejecutados, pero las lecciones son genericas. | H32: 3 | I32: 0 | J32: Cierre coherente y sin incidencias finales. | K32: 3 | L32: 3 | M32: =IF(AND(K32>0,L32<>""),L32/K32*100,"") | N32: =IF(M32="","",IF(M32<25,"0-25 ausente/residual",IF(M32<50,"25-50 parcial",IF(M32<75,"50-75 sustancial","75-100 alta")))) | O32: Los tres documentos de cierre enlazan con validacion final, entrega y aprendizaje del run. | P32: 1 | Q32: 0 | R32: 0 | S32: 1 | T32: =SUM(P32:S32)
A34: Nota M5 (memoria, cap. 9): la huella de gobernanza acredita G1 (decisión) y G4 (aprobación) solo en fases con gate humano. En sprints y cierre del pipeline, sin gate, G1 y G4 no se acreditan.
A35: La media de M5 reportada es el promedio de las cinco familias. Baseline·Requisitos = 3 (G1,G2,G3,G4 = 1,1,1,0).
A36: Valores finales M5 (media por caso): Baseline 2,40 · Run 01 1,27 · Run 02 1,67 · Run 03 1,33. Media del pipeline 1,42.

Sheet 06_P1_P2_pruebas
A1: P1/P2 — Validación técnica del producto + suite de pruebas funcionales
A2: La suite es la misma para baseline y para los 3 runs IA. Replica las columnas de resultado por cada caso. M6 = % funcionalidades implementadas; M7 = % tests pasados.
A4: ID test | B4: Área | C4: Objetivo | D4: Prioridad | E4: Tipo evaluación | F4: Resultado Baseline (PASS/FAIL/ MANUAL/PARCIAL) | G4: Resultado Run 01 | H4: Resultado Run 02 | I4: Resultado Run 03 | J4: Métricas | K4: Evidencia / Observaciones
A5: T-AUTH-01 | B5: Autenticación | C5: Registro de cliente | D5: Alta | E5: MANUAL | F5: PASS | G5: PASS | H5: PASS | I5: PASS | J5: M6,M7 | K5: RUN 01: Validaciones de formulario incluidas. RUN 02: Mejor interfaz que RUN 01. RUN 03: La mejor interfaz de los demas Runs.
A6: T-AUTH-02 | B6: Autenticación | C6: Login de usuario | D6: Alta | E6: AUTOMATICA | F6: PASS | G6: PASS | H6: PASS | I6: PASS | J6: M6,M7
A7: T-AUTH-03 | B7: Autenticación | C7: Logout explícito | D7: Alta | E7: AUTOMATICA | F7: PASS | G7: PASS | H7: FAIL | I7: PASS | J7: M6,M7 | K7: RUN 02: Inicio sesion pero luego no aparece el boton para cerrar sesion. Aparece en otras interfaces, no es visible siempre.
A8: T-CAT-01 | B8: Catálogo | C8: Listado de barcos | D8: Alta | E8: AUTOMATICA | F8: PASS | G8: PASS | H8: PASS | I8: PASS | J8: M6,M7
A9: T-CAT-02 | B9: Catálogo | C9: Ficha de barco | D9: Alta | E9: AUTOMATICA | F9: PASS | G9: PASS | H9: PASS | I9: PASS | J9: M6,M7
A10: T-CAT-03 | B10: Catálogo | C10: Búsqueda por nombre | D10: Alta | E10: AUTOMATICA | F10: PASS | G10: PASS | H10: PASS | I10: PASS | J10: M6,M7
A11: T-CAT-04 | B11: Catálogo | C11: Filtro por puerto | D11: Media | E11: AUTOMATICA | F11: PASS | G11: PASS | H11: PASS | I11: PASS | J11: M6,M7
A12: T-CAT-05 | B12: Catálogo | C12: Filtro por fabricante | D12: Media | E12: AUTOMATICA | F12: PASS | G12: PASS | H12: PASS | I12: PASS | J12: M6,M7
A13: T-CAT-06 | B13: Catálogo | C13: Filtros combinados | D13: Alta | E13: AUTOMATICA | F13: PASS | G13: PASS | H13: PASS | I13: PASS | J13: M6,M7
A14: T-CAT-07 | B14: Catálogo | C14: Disponibilidad por fechas | D14: Alta | E14: MANUAL | F14: PASS | G14: PASS | H14: PASS | I14: PASS | J14: M6,M7 | K14: BASELINE: Suele contener toda la edicion para continuar, fechas , cantidad, y un detalle de los pagos conforme hace los cambios. RUN 02: La colocacion de fechas esta dentro de los pasos de reserva.
A15: T-CART-01 | B15: Cesta | C15: Añadir barco a cesta | D15: Alta | E15: MANUAL | F15: PASS | G15: PASS | H15: PASS | I15: PASS | J15: M6,M7
A16: T-CART-02 | B16: Cesta | C16: Modificar cantidad/fechas | D16: Alta | E16: MANUAL | F16: PASS | G16: PASS | H16: PASS | I16: PASS | J16: M6,M7 | K16: RUN 01: Se modifica antes de enviar a la cesta, luego ya no se puede. RUN 02: Editar fechas y cantidad estan separadas. RUN 03: Separa dentro del proceso de reserva.
A17: T-CART-03 | B17: Cesta | C17: Cesta accesible | D17: Media | E17: AUTOMATICA | F17: PASS | G17: PASS | H17: PASS | I17: PASS | J17: M6,M7
A18: T-RES-01 | B18: Reserva | C18: Reserva sin registro | D18: Alta | E18: MIXTA | F18: PASS | G18: PASS | H18: FAIL | I18: FAIL | J18: M6,M7 | K18: RUN 02: GET /reserva/paso2/ HTTP/1.1 500 RUN 03: GET /reserva/paso2/ HTTP/1.1 500 Error de renderizado de template
A19: T-RES-02 | B19: Reserva | C19: Reserva con usuario registrado | D19: Alta | E19: MANUAL | F19: PASS | G19: PASS | H19: FAIL | I19: FAIL | J19: M6,M7 | K19: RUN 02: GET /reserva/paso2/ HTTP/1.1 500 RUN 03: Error de renderizado de template
A20: T-RES-03 | B20: Reserva | C20: Checkout máximo tres pasos | D20: Alta | E20: MIXTA | F20: PASS | G20: PASS | H20: FAIL | I20: FAIL | J20: M6,M7 | K20: RUN 02: No se puede comprobar debido al error anterior. RUN 03: No se puede comprobar debido al error anterior.
A21: T-RES-04 | B21: Reserva | C21: Tasa combustible | D21: Media | E21: MIXTA | F21: PASS | G21: PASS | H21: FAIL | I21: PASS | J21: M6,M7 | K21: BASELINE: Lo presenta detallado en el proceso de reserva según corresponda, el cliente sabe si pagar una tasa de combustible. RUN 01: La tasa de combustible viene implicitamente en el precio, no hay detalle del pago, parece que no estuviera considerado. Para el ADMIN las reservas si estan detallados y la tasa de combustible esta presente. RUN 02: No se puede hacer reserva. RUN 03: Al enviar un producto a la cesta se especificado si corresponde pagar una tasa de combustible. El precio esta especificado y desglosado.
A22: T-PAY-01 | B22: Pago | C22: Contra-reembolso | D22: Alta | E22: AUTOMATICA | F22: PASS | G22: PASS | H22: FAIL | I22: FAIL | J22: M6,M7 | K22: RUN 02: No se puede completar la reserva. RUN 03: No se puede completar reserva
A23: T-PAY-02 | B23: Pago | C23: PayPal Sandbox visible | D23: Alta | E23: AUTOMATICA | F23: PASS | G23: PASS | H23: FAIL | I23: FAIL | J23: M6,M7 | K23: RUN 02: No se puede completar la reserva. RUN 03: No se puede completar reserva
A24: T-TRACK-01 | B24: Seguimiento | C24: Código seguimiento generado | D24: Alta | E24: AUTOMATICA | F24: PASS | G24: PASS | H24: FAIL | I24: FAIL | J24: M6,M7 | K24: RUN 02: No se puede completar la reserva y tampoco hay alguna señal de que se pueda consultar la reserva con el codigo.
A25: T-TRACK-02 | B25: Seguimiento | C25: Consulta por código sin login | D25: Alta | E25: AUTOMATICA | F25: PASS | G25: PASS | H25: FAIL | I25: FAIL | J25: M6,M7 | K25: RUN 02: No se puede completar la reserva y tampoco hay alguna señal de que se pueda consultar la reserva con el codigo.
A26: T-TRACK-03 | B26: Seguimiento | C26: Cancelación sólo pendiente | D26: Media | E26: MANUAL | F26: FAIL | G26: PASS | H26: FAIL | I26: FAIL | J26: M6,M7 | K26: Baseline: Esto no esta implementado. RUN 02: No se puede completar la reserva y tampoco hay alguna señal de que se pueda consultar la reserva con el codigo.
A27: T-ADMIN-01 | B27: Admin | C27: Acceso panel admin propio | D27: Alta | E27: AUTOMATICA | F27: PASS | G27: PASS | H27: FAIL | I27: FAIL | J27: M6,M7 | K27: RUN 01: Dificil de acceder poque no especifica de manera sencilla las credenciales para acceder al panel de ADMIN. RUN 02: No hay acceso al panel de admin. RUN 03: No hay acceso al panel de admin. Error de resolución de URL en template
A28: T-ADMIN-02 | B28: Admin | C28: Gestión catálogo | D28: Alta | E28: AUTOMATICA | F28: PASS | G28: PASS | H28: FAIL | I28: FAIL | J28: M6,M7 | K28: RUN 02: No hay panel de admin. RUN 03: No hay panel de admin.
A29: T-ADMIN-03 | B29: Admin | C29: Gestión clientes | D29: Alta | E29: AUTOMATICA | F29: PASS | G29: PASS | H29: FAIL | I29: FAIL | J29: M6,M7 | K29: RUN 02: No hay panel de admin. RUN 03: No hay panel de admin.
... A31: T-ADMIN-05 | B31: Admin | C31: Restricción eliminar cliente con reservas | D31: Alta | E31: AUTOMATICA | F31: PASS | G31: PASS | H31: FAIL | I31: FAIL | J31: M6,M7 | K31: RUN 02: No hay panel de admin. RUN 03: No hay panel de admin.
A33: MÉTRICAS RESUMEN
A34: Total tests | B34: =COUNTA(A5:A31)
A35: Tests pasados Baseline (PASS) | B35: =COUNTIF(F5:F31,"PASS")
A36: Tests pasados Run 01 (PASS) | B36: =COUNTIF(G5:G31,"PASS")
A37: Tests pasados Run 02 (PASS) | B37: =COUNTIF(H5:H31,"PASS")
A38: Tests pasados Run 03 (PASS) | B38: =COUNTIF(I5:I31,"PASS")
A39: M7 Baseline (%) | B39: =IF(B34>0,B35/B34*100,0)
A40: M7 Run 01 (%) | B40: =IF(B34>0,B36/B34*100,0)
A41: M7 Run 02 (%) | B41: =IF(B34>0,B37/B34*100,0)
A42: M7 Run 03 (%) | B42: =IF(B34>0,B38/B34*100,0)
A45: M6 IMPLEMENTATION RATE — Funcionalidades implementadas (manual) Criterio M6. Para el cálculo de Implementation Rate solo se contabilizan como implementadas completas las funcionalidades marcadas como "Sí". Las funcionalidades marcadas como "No" o "Parcial" no suman en el numerador de M6. El valor "Parcial" se conserva como evidencia cualitativa para el análisis de VD2, pero no incrementa el porcentaje de implementación.
A46: Funcionalidad | B46: Baseline | C46: Run 01 | D46: Run 02 | E46: Run 03
A47: Registro de usuario | B47: Sí | C47: Sí | D47: Sí | E47: Sí
A48: Login/logout | B48: Sí | C48: Sí | D48: Parcial | E48: Sí
A49: Catálogo/listado | B49: Sí | C49: Sí | D49: Sí | E49: Sí
A50: Búsqueda/filtrado | B50: Sí | C50: Sí | D50: Sí | E50: Sí
A51: Selección fechas/disponibilidad | B51: Sí | C51: Sí | D51: Sí | E51: Sí
A52: Checkout/reserva | B52: Sí | C52: Sí | D52: No | E52: No
A53: Pago simulado | B53: Sí | C53: Sí | D53: No | E53: No
A54: Panel administración | B54: Sí | C54: Sí | D54: No | E54: No
A55: Gestión catálogo admin | B55: Sí | C55: Sí | D55: No | E55: No
A56: Gestión reservas admin | B56: Sí | C56: Sí | D56: No | E56: No
A57: N total | B57: =COUNTA(A47:A56) | C57: =COUNTA(A47:A56) | D57: =COUNTA(A47:A56) | E57: =COUNTA(A47:A56)
A58: Implementadas completas ("Sí") | B58: =COUNTIF(B47:B56,"Sí") | C58: =COUNTIF(C47:C56,"Sí") | D58: =COUNTIF(D47:D56,"Sí") | E58: =COUNTIF(E47:E56,"Sí")
A59: M6 (%) — completas / total | B59: =IF(B57>0,B58/B57*100,0) | C59: =IF(C57>0,C58/C57*100,0) | D59: =IF(D57>0,D58/D57*100,0) | E59: =IF(E57>0,E58/E57*100,0)
A61: M-OPERATIVIDAD (0=no arranca, 1=arranca pero flujo incompleto, 2=arranca y flujo mínimo completo)
A62: Caso | B62: M-operatividad (0/1/2) | C62: Evidencia
A63: Baseline | B63: 2 | C63: Cumple con el PMV
A64: Run 01 | B64: 2 | C64: Cumple con el PMV
A65: Run 02 | B65: 1 | C65: El producto funciona pero no tiene todas las funcionalidades minimas.
A66: Run 03 | B66: 1 | C66: El producto funciona pero no tiene todas las funcionalidades minimas.

Sheet 07_T1_T2_T3_tiempos
A1: T1/T2/T3 — Tiempos y esfuerzo humano (H1: M17; auxiliares M15, M18; descriptiva M16)
A2: Registra cada bloque temporal con fase, tipo y duración en minutos. T1 recoge ejecución automática IA (M16 descriptiva), T2 recoge esfuerzo humano/gate IA (M17) y T3 recoge tiempos baseline reconstruidos. M15 se lee como tiempo por fase/sprint; M18 resume iteraciones adicionales cuando exista evidencia.
A4: ID | B4: Caso | C4: Run | D4: Fase/Sprint/Gate | E4: Tipo tiempo | F4: Duración (min) | G4: Fuente | H4: Regla 7 | I4: ¿Cota inferior? | J4: Observaciones
A5: T-B-01 | B5: Baseline | C5: — | D5: Requisitos | E5: Elaboración humana | F5: 480 | G5: 04_codigo\04a_casoBase\documentacion\INICIO\ACTA DE CONSTITUCIÓN.pdf + 04_codigo\04a_casoBase\documentacion\ACTAS\Acta Reunión semana 1.pdf + 04_codigo\04a_casoBase\documentacion\PLANIFICACIÓN\LINEAS BASE\LISTA DE HITOS.pdf | H5: Reconstruida | I5: No | J5: Inicio / acta inicial: 8 h de trabajo estimado. Fuente exacta completada desde documentaci?n baseline completa.
A6: T-B-02 | B6: Baseline | C6: — | D6: Planificación | E6: Elaboración humana | F6: 7680 | G6: 04_codigo\04a_casoBase\documentacion\PLANIFICACIÓN\LINEAS BASE\CRONOGRAMA Y PRESUPUESTO.pdf + 04_codigo\04a_casoBase\documentacion\PLANIFICACIÓN\LINEAS BASE\DICCIONARIO DE LA EDT.pdf + 04_codigo\04a_casoBase\documentacion\PLANIFICACIÓN\LINEAS BASE\ATRIBUTOS DE ACTIVIDAD.pdf + 04_codigo\04a_casoBase\documentacion\PLANIFICACIÓN\PLANES\PLAN DE GESTION DEL CRONOGRAMA.pdf | H6: Reconstruida | I6: No | J6: Planificación general: 128 h. Fuente exacta completada desde documentaci?n baseline completa.
A7: T-B-03 | B7: Baseline | C7: — | D7: Sprint 1 — Desarrollo | E7: Elaboración humana | F7: 1920 | G7: 04_codigo\04a_casoBase\documentacion\PLANIFICACIÓN\LINEAS BASE\CRONOGRAMA Y PRESUPUESTO.pdf + 04_codigo\04a_casoBase\documentacion\EJECUCIÓN\Sprint 1\Sprint 1 - Planning.pdf + 04_codigo\04a_casoBase\documentacion\EJECUCIÓN\Sprint 1\Sprint 1 - Product Backlog.pdf | H7: Reconstruida | I7: No | J7: Sprint 1 / Prototipo 1: 32 h. Fuente exacta completada desde documentaci?n baseline completa.
A8: T-B-04 | B8: Baseline | C8: — | D8: Sprint 1 — Revisión | E8: Revisión/gate | F8: 270 | G8: 04_codigo\04a_casoBase\documentacion\ACTAS\Acta Reunión semana 1.pdf + 04_codigo\04a_casoBase\documentacion\ACTAS\Acta Reunión semana 3.pdf + 04_codigo\04a_casoBase\documentacion\ACTAS\Acta Reunión estimación de tareas y costes.pdf | H8: Reconstruida | I8: Sí | J8: Reuniones de equipo: semana 1, semana 3 y estimación (4,50 h). Fuente exacta completada desde documentaci?n baseline completa.
A9: T-B-05 | B9: Baseline | C9: — | D9: Sprint 2 — Desarrollo | E9: Elaboración humana | F9: 1680 | G9: 04_codigo\04a_casoBase\documentacion\PLANIFICACIÓN\LINEAS BASE\CRONOGRAMA Y PRESUPUESTO.pdf + 04_codigo\04a_casoBase\documentacion\EJECUCIÓN\Sprint 2\Sprint 2 - Planning.pdf + 04_codigo\04a_casoBase\documentacion\EJECUCIÓN\Sprint 2\Sprint 2 - Product Backlog.pdf | H9: Reconstruida | I9: No | J9: Sprint 2 / Prototipo 2: 28 h. Fuente exacta completada desde documentaci?n baseline completa.
A10: T-B-06 | B10: Baseline | C10: — | D10: Sprint 2 — Revisión | E10: Revisión/gate | F10: 220 | G10: 04_codigo\04a_casoBase\documentacion\ACTAS\Acta Patrocinador 1.pdf + 04_codigo\04a_casoBase\documentacion\ACTAS\Acta Patrocinador 2.pdf | H10: Reconstruida | I10: Sí | J10: Reuniones patrocinador 1 y 2 (3,67 h aprox.). Fuente exacta completada desde documentaci?n baseline completa.
A11: T-B-07 | B11: Baseline | C11: — | D11: Sprint 3 — Desarrollo | E11: Elaboración humana | F11: 1440 | G11: 04_codigo\04a_casoBase\documentacion\PLANIFICACIÓN\LINEAS BASE\CRONOGRAMA Y PRESUPUESTO.pdf + 04_codigo\04a_casoBase\documentacion\EJECUCIÓN\Sprint 3\Sprint 3 - Planning.pdf + 04_codigo\04a_casoBase\documentacion\EJECUCIÓN\Sprint 3\Sprint 3 - Product Backlog.pdf + 04_codigo\04a_casoBase\documentacion\CIERRE\Manual de Despliegue en Docker.pdf | H11: Reconstruida | I11: No | J11: Sprint 3 / Prototipo 3: 24 h; incluye pruebas y manual/despliegue. Fuente exacta completada desde documentaci?n baseline completa.
A12: T-B-08 | B12: Baseline | C12: — | D12: Sprint 3 — Revisión | E12: Revisión/gate | F12: 220 | G12: 04_codigo\04a_casoBase\documentacion\ACTAS\Acta Patrocinador 3.pdf + 04_codigo\04a_casoBase\documentacion\ACTAS\Acta Patrocinador 4.pdf | H12: Reconstruida | I12: Sí | J12: Reuniones patrocinador 3 y 4 (3,67 h aprox.). Fuente exacta completada desde documentaci?n baseline completa.
A13: T-B-09 | B13: Baseline | C13: — | D13: Cierre — Lecciones/Informe | E13: Elaboración humana | F13: 1440 | G13: 04_codigo\04a_casoBase\documentacion\CIERRE\Lecciones aprendidas.pdf + 04_codigo\04a_casoBase\documentacion\CIERRE\Informe de cierre.pdf + 04_codigo\04a_casoBase\documentacion\SEGUIMIENTO\Cierre\Informe de Seguimiento - Cierre.pdf + 04_codigo\04a_casoBase\documentacion\SEGUIMIENTO\Cierre\Valor Ganado Cierre.pdf | H13: Reconstruida | I13: No | J13: Seguimiento 16 h + cierre 8 h; manual ya incluido en Sprint 3. Fuente exacta completada desde documentaci?n baseline completa.
A14: T-run_01-EJ-REQ | B14: Pipeline | C14: run_01 | D14: Fase 01 Requisitos | E14: Ejecución automática | F14: 0.33 | G14: IA_OFICIAL_01/00_manifest/run_summary.json + manifest.json | H14: Original | I14: No | J14: run_id=run_2026-05-18_15-09; tiempos en segundos convertidos a minutos.
A15: T-run_01-GA-REQ | B15: Pipeline | C15: run_01 | D15: Gate 1 Requisitos | E15: Revisión/gate | F15: 19.51 | G15: IA_OFICIAL_01/00_manifest/run_summary.json + manifest.json | H15: Original | I15: No | J15: run_id=run_2026-05-18_15-09; tiempos en segundos convertidos a minutos.
A16: T-run_01-EJ-PLAN | B16: Pipeline | C16: run_01 | D16: Fase 02 Planificación | E16: Ejecución automática | F16: 1.01 | G16: IA_OFICIAL_01/00_manifest/run_summary.json + manifest.json | H16: Original | I16: No | J16: run_id=run_2026-05-18_15-09; tiempos en segundos convertidos a minutos.
... A37: T-run_03-EJ-CIE | B37: Pipeline | C37: run_03 | D37: Cierre | E37: Ejecución automática | F37: 0.11 | G37: IA_OFICIAL_03/00_manifest/run_summary.json + manifest.json | H37: Original | I37: No | J37: run_id=run_2026-05-19_02-15; tiempos en segundos convertidos a minutos.
A40: AGREGADOS H1
A41: Concepto | B41: Baseline (min) | C41: Pipeline run_01 | D41: Pipeline run_02 | E41: Pipeline run_03 | F41: Pipeline media
A42: M16 — Tiempo activo de elaboración IA por fase (descriptiva, no contrasta H1) | B42: ? | C42: =SUMIFS(F5:F37,B5:B37,"Pipeline",C5:C37,"run_01",E5:E37,"Ejecución automática") | D42: =SUMIFS(F5:F37,B5:B37,"Pipeline",C5:C37,"run_02",E5:E37,"Ejecución automática") | E42: =SUMIFS(F5:F37,B5:B37,"Pipeline",C5:C37,"run_03",E5:E37,"Ejecución automática") | F42: =AVERAGE(C42:E42)
A43: M17 — Esfuerzo humano de supervisión/gate | B43: =SUMIFS(F5:F37,B5:B37,"Baseline",E5:E37,"Revisión/gate") | C43: =SUMIFS(F5:F37,B5:B37,"Pipeline",C5:C37,"run_01",E5:E37,"Revisión/gate") | D43: =SUMIFS(F5:F37,B5:B37,"Pipeline",C5:C37,"run_02",E5:E37,"Revisión/gate") | E43: =SUMIFS(F5:F37,B5:B37,"Pipeline",C5:C37,"run_03",E5:E37,"Revisión/gate") | F43: =AVERAGE(C43:E43)
A44: M15 — Tiempo humano de elaboración baseline (contexto por fase/sprint) | B44: =SUMIFS(F5:F37,B5:B37,"Baseline",E5:E37,"Elaboración humana") | C44: ? | D44: ? | E44: ? | F44: ?
A45: TOTAL M17 — Baseline (solo revisión/gate) | B45: =B43 | C45: ? | D45: ? | E45: ? | F45: ?
A46: TOTAL M17 — Pipeline (solo revisión/gate) | B46: ? | C46: =C43 | D46: =D43 | E46: =E43 | F46: =AVERAGE(C46:E46)
A47: Diferencia M17 (pipeline - baseline) | C47: =C46-B45 | D47: =D46-B45 | E47: =E46-B45 | F47: =F46-B45
A48: % Diferencia M17 respecto a baseline | C48: =IF(B45>0,(C46-B45)/B45*100,0) | D48: =IF(B45>0,(D46-B45)/B45*100,0) | E48: =IF(B45>0,(E46-B45)/B45*100,0) | F48: =IF(B45>0,(F46-B45)/B45*100,0)
A49: VEREDICTO H1 (M17: esfuerzo humano directo) | F49: =IF(F48<=-20,"CONFIRMADA",IF(F48<0,"PARCIALMENTE SOSTENIDA","RECHAZADA"))

Sheet 08_I1_incidencias
A1: I1 — Incidencias y deriva (H3: M14, M9, M10, M11, M12; descriptiva M13)
A2: Una fila por incidencia. M14 = subset con tipo 'Deriva de alcance' Y origen='Stakeholder' o cambio no controlado.
A4: ID incidencia | B4: Caso | C4: Run | D4: Fase detección (M11) | E4: Tipo (M9) | F4: Origen | G4: Severidad (M10) | H4: Coste corrección (min) (M12) | I4: ¿Detectada en gate? | J4: ¿Cuenta para M14? | K4: Descripción | L4: Evidencia
A5: INC-B-01 | B5: Baseline | C5: — | D5: Sprint 1 | E5: Deriva funcional | F5: Stakeholder | G5: Media | I5: No | J5: Sí | K5: Cambio de formato de reserva: de días a calendario (solicitado por patrocinador). | L5: 04_codigo\04a_casoBase\documentacion\EJECUCIÓN\REGISTRO DE INCIDENCIAS.pdf (ID 1, 20/11/2024) + 04_codigo\04a_casoBase\documentacion\EJECUCIÓN\REGISTRO DE CAMBIOS.pdf (ID 1, 18/11/2024) + 04_codigo\04a_casoBase\documentacion\EJECUCIÓN\Solicitud de cambio_01.pdf
A6: INC-B-02 | B6: Baseline | C6: — | D6: Sprint 2 | E6: Error técnico | F6: Humano | G6: Alta | I6: No | J6: Sí | K6: Problemas implementación Stripe; reemplazado por PayPal en sprint posterior. | L6: 04_codigo\04a_casoBase\documentacion\EJECUCIÓN\REGISTRO DE INCIDENCIAS.pdf (ID 2, 23/11/2024) + 04_codigo\04a_casoBase\documentacion\EJECUCIÓN\REGISTRO DE CAMBIOS.pdf (ID 2, 23/11/2024) + 04_codigo\04a_casoBase\documentacion\EJECUCIÓN\Solicitud de cambio_02.pdf
A7: INC-B-03 | B7: Baseline | C7: — | D7: Sprint 3 | E7: Error funcional | F7: Humano | G7: Baja | I7: No | J7: No | K7: Filtros del catálogo no podían seleccionarse a la vez (defecto funcional detectado en ejecución). | L7: 04_codigo\04a_casoBase\documentacion\EJECUCIÓN\REGISTRO DE INCIDENCIAS.pdf (ID 3, 04/12/2024) + 04_codigo\04a_casoBase\documentacion\EJECUCIÓN\REGISTRO DE CAMBIOS.pdf + 04_codigo\04a_casoBase\documentacion\EJECUCIÓN\Solicitud de cambio_03.pdf
A8: INC-B-04 | B8: Baseline | C8: — | D8: Sprint 3 | E8: Error funcional | F8: Humano | G8: Media | I8: No | J8: No | K8: No se podía indicar la cantidad del producto en el catálogo. | L8: 04_codigo\04a_casoBase\documentacion\EJECUCIÓN\REGISTRO DE INCIDENCIAS.pdf (ID 4, 04/12/2024) + 04_codigo\04a_casoBase\documentacion\EJECUCIÓN\REGISTRO DE CAMBIOS.pdf + 04_codigo\04a_casoBase\documentacion\EJECUCIÓN\Solicitud de cambio_04.pdf
A9: INC-B-05 | B9: Baseline | C9: — | D9: Sprint 3 | E9: Error funcional | F9: Humano | G9: Media | I9: No | J9: No | K9: No se incluía la opción de inicio de sesión en el proceso de compra. | L9: 04_codigo\04a_casoBase\documentacion\EJECUCIÓN\REGISTRO DE INCIDENCIAS.pdf (ID 5, 04/12/2024) + 04_codigo\04a_casoBase\documentacion\EJECUCIÓN\REGISTRO DE CAMBIOS.pdf + 04_codigo\04a_casoBase\documentacion\EJECUCIÓN\Solicitud de cambio_05.pdf
A10: CAM-B-01 | B10: Baseline | C10: — | D10: Planificación | E10: Deriva funcional | F10: Stakeholder | G10: Media | I10: No | J10: Sí | K10: Despliegue temprano aprobado (cambio de cronograma del patrocinador). | L10: Registro de Cambios Hundidos, ID 1 (18/11/2024).
A11: CAM-B-02 | B11: Baseline | C11: — | D11: Sprint 2 | E11: Deriva funcional | F11: Humano | G11: Alta | I11: No | J11: Sí | K11: Atraso del sistema de pagos: finalización diferida al siguiente sprint. | L11: Registro de Cambios Hundidos, ID 2 (23/11/2024).
A12: CAM-B-03 | B12: Baseline | C12: — | D12: Planificación | E12: Deriva funcional | F12: Humano | G12: Media | I12: No | J12: Sí | K12: Cambio de requisitos aprobado (alcance modificado durante ejecución). | L12: Registro de Cambios Hundidos, ID 3 (30/11/2024).
A13: CAM-B-04 | B13: Baseline | C13: — | D13: Planificación | E13: Deriva funcional | F13: Humano | G13: Media | I13: No | J13: Sí | K13: Cambio de cronograma aprobado (replanificación de fechas). | L13: Registro de Cambios Hundidos, ID 4 (30/11/2024).
A14: CAM-B-05 | B14: Baseline | C14: — | D14: Planificación | E14: Deriva funcional | F14: Humano | G14: Media | I14: No | J14: Sí | K14: Cambio de cronograma aprobado (segunda replanificación). | L14: Registro de Cambios Hundidos, ID 5 (03/12/2024).
A15: INC-IA-R01-01 | B15: Pipeline | C15: run_01 | D15: Sprint 1 | E15: Error técnico | F15: Agente | G15: Alta | I15: No | J15: Sí | K15: Templates reservations/cart.html y reservations/step1.html no compilan: filtro "mul" no existe en Django (TemplateSyntaxError). | L15: review_sprint_1.json (run_2026-05-18_15-09), campo incidencias[].
A16: INC-IA-R01-02 | B16: Pipeline | C16: run_01 | D16: Sprint 1 | E16: Fallo de validación | F16: Validación | G16: Media | I16: No | J16: Sí | K16: Ruta /cesta/ no responde (TimeoutError) en el review automático de Sprint 1. | L16: review_sprint_1.json (run_2026-05-18_15-09), campo incidencias[].
... A32: INC-IA-COMUN-03-03 | B32: Pipeline | C32: run_03 | D32: Diseño | E32: Error técnico | F32: Agente | G32: Baja | I32: Sí | J32: No | K32: Campo ImageField del diseño técnico declarado como upload_to=barcos/ sin comillas (cadena no válida). Consecuencia operativa: no se muestran imágenes en el producto generado en ninguno de los 3 runs, aunque no genera error de arranque. | L32: gate_humano.md fase 03 arquitectura (observación no bloqueante en los 3 runs).
A34: AGREGADOS H3
A35: Métrica | B35: Baseline | C35: Run 01 | D35: Run 02 | E35: Run 03 | F35: Pipeline media
A36: Total incidencias | B36: =COUNTIFS(B5:B32,"Baseline") | C36: =COUNTIFS(B5:B32,"Pipeline",C5:C32,"run_01") | D36: =COUNTIFS(B5:B32,"Pipeline",C5:C32,"run_02") | E36: =COUNTIFS(B5:B32,"Pipeline",C5:C32,"run_03") | F36: =AVERAGE(C36:E36)
A37: M14 — Cambios por malinterpretación/reinterpretación | B37: =COUNTIFS(B5:B32,"Baseline",J5:J32,"Sí") | C37: =COUNTIFS(B5:B32,"Pipeline",C5:C32,"run_01",J5:J32,"Sí") | D37: =COUNTIFS(B5:B32,"Pipeline",C5:C32,"run_02",J5:J32,"Sí") | E37: =COUNTIFS(B5:B32,"Pipeline",C5:C32,"run_03",J5:J32,"Sí") | F37: =AVERAGE(C37:E37)
A38: M9 — Incidencias por tipo: Deriva funcional | B38: =COUNTIFS(B5:B32,"Baseline",E5:E32,"Deriva funcional") | C38: =COUNTIFS(B5:B32,"Pipeline",C5:C32,"run_01",E5:E32,"Deriva funcional") | D38: =COUNTIFS(B5:B32,"Pipeline",C5:C32,"run_02",E5:E32,"Deriva funcional") | E38: =COUNTIFS(B5:B32,"Pipeline",C5:C32,"run_03",E5:E32,"Deriva funcional") | F38: =AVERAGE(C38:E38)
A39: M13 — Incidencias detectadas por gate (%) | B39: ? | C39: =IF(C36>0,COUNTIFS(B5:B32,"Pipeline",C5:C32,"run_01",I5:I32,"Sí")/C36*100,0) | D39: =IF(D36>0,COUNTIFS(B5:B32,"Pipeline",C5:C32,"run_02",I5:I32,"Sí")/D36*100,0) | E39: =IF(E36>0,COUNTIFS(B5:B32,"Pipeline",C5:C32,"run_03",I5:I32,"Sí")/E36*100,0) | F39: =AVERAGE(C39:E39)
A40: VEREDICTO H3 (M14_IA < M14_baseline y % derivas detectadas en gate > 50%) | F40: PARCIALMENTE SOSTENIDA — menos derivas que el baseline; detección de derivas en gate = 38,89 % < 50 %
A44: Agregados auxiliares H3
A45: Métrica | B45: Detalle | C45: Baseline | D45: Run 01 | E45: Run 02 | F45: Run 03 | G45: Media
A46: M9 | B46: Deriva funcional | C46: =COUNTIFS($B$5:$B$32,"Baseline",$E$5:$E$32,B46) | D46: =COUNTIFS($B$5:$B$32,"Pipeline",$C$5:$C$32,"run_01",$E$5:$E$32,B46) | E46: =COUNTIFS($B$5:$B$32,"Pipeline",$C$5:$C$32,"run_02",$E$5:$E$32,B46) | F46: =COUNTIFS($B$5:$B$32,"Pipeline",$C$5:$C$32,"run_03",$E$5:$E$32,B46) | G46: =AVERAGE(D46:F46)
A47: M9 | B47: Error técnico | C47: =COUNTIFS($B$5:$B$32,"Baseline",$E$5:$E$32,B47) | D47: =COUNTIFS($B$5:$B$32,"Pipeline",$C$5:$C$32,"run_01",$E$5:$E$32,B47) | E47: =COUNTIFS($B$5:$B$32,"Pipeline",$C$5:$C$32,"run_02",$E$5:$E$32,B47) | F47: =COUNTIFS($B$5:$B$32,"Pipeline",$C$5:$C$32,"run_03",$E$5:$E$32,B47) | G47: =AVERAGE(D47:F47)
A48: M9 | B48: Error funcional | C48: =COUNTIFS($B$5:$B$32,"Baseline",$E$5:$E$32,B48) | D48: =COUNTIFS($B$5:$B$32,"Pipeline",$C$5:$C$32,"run_01",$E$5:$E$32,B48) | E48: =COUNTIFS($B$5:$B$32,"Pipeline",$C$5:$C$32,"run_02",$E$5:$E$32,B48) | F48: =COUNTIFS($B$5:$B$32,"Pipeline",$C$5:$C$32,"run_03",$E$5:$E$32,B48) | G48: =AVERAGE(D48:F48)
A49: M9 | B49: Fallo de validación | C49: =COUNTIFS($B$5:$B$32,"Baseline",$E$5:$E$32,B49) | D49: =COUNTIFS($B$5:$B$32,"Pipeline",$C$5:$C$32,"run_01",$E$5:$E$32,B49) | E49: =COUNTIFS($B$5:$B$32,"Pipeline",$C$5:$C$32,"run_02",$E$5:$E$32,B49) | F49: =COUNTIFS($B$5:$B$32,"Pipeline",$C$5:$C$32,"run_03",$E$5:$E$32,B49) | G49: =AVERAGE(D49:F49)
A50: M9 | B50: Incoherencia documental | C50: =COUNTIFS($B$5:$B$32,"Baseline",$E$5:$E$32,B50) | D50: =COUNTIFS($B$5:$B$32,"Pipeline",$C$5:$C$32,"run_01",$E$5:$E$32,B50) | E50: =COUNTIFS($B$5:$B$32,"Pipeline",$C$5:$C$32,"run_02",$E$5:$E$32,B50) | F50: =COUNTIFS($B$5:$B$32,"Pipeline",$C$5:$C$32,"run_03",$E$5:$E$32,B50) | G50: =AVERAGE(D50:F50)
A52: M10 | B52: Alta | C52: =COUNTIFS($B$5:$B$32,"Baseline",$G$5:$G$32,B52) | D52: =COUNTIFS($B$5:$B$32,"Pipeline",$C$5:$C$32,"run_01",$G$5:$G$32,B52) | E52: =COUNTIFS($B$5:$B$32,"Pipeline",$C$5:$C$32,"run_02",$G$5:$G$32,B52) | F52: =COUNTIFS($B$5:$B$32,"Pipeline",$C$5:$C$32,"run_03",$G$5:$G$32,B52) | G52: =AVERAGE(D52:F52)
A53: M10 | B53: Media | C53: =COUNTIFS($B$5:$B$32,"Baseline",$G$5:$G$32,B53) | D53: =COUNTIFS($B$5:$B$32,"Pipeline",$C$5:$C$32,"run_01",$G$5:$G$32,B53) | E53: =COUNTIFS($B$5:$B$32,"Pipeline",$C$5:$C$32,"run_02",$G$5:$G$32,B53) | F53: =COUNTIFS($B$5:$B$32,"Pipeline",$C$5:$C$32,"run_03",$G$5:$G$32,B53) | G53: =AVERAGE(D53:F53)
A54: M10 | B54: Baja | C54: =COUNTIFS($B$5:$B$32,"Baseline",$G$5:$G$32,B54) | D54: =COUNTIFS($B$5:$B$32,"Pipeline",$C$5:$C$32,"run_01",$G$5:$G$32,B54) | E54: =COUNTIFS($B$5:$B$32,"Pipeline",$C$5:$C$32,"run_02",$G$5:$G$32,B54) | F54: =COUNTIFS($B$5:$B$32,"Pipeline",$C$5:$C$32,"run_03",$G$5:$G$32,B54) | G54: =AVERAGE(D54:F54)
A56: M11 | B56: Requisitos | C56: =COUNTIFS($B$5:$B$32,"Baseline",$D$5:$D$32,B56) | D56: =COUNTIFS($B$5:$B$32,"Pipeline",$C$5:$C$32,"run_01",$D$5:$D$32,B56) | E56: =COUNTIFS($B$5:$B$32,"Pipeline",$C$5:$C$32,"run_02",$D$5:$D$32,B56) | F56: =COUNTIFS($B$5:$B$32,"Pipeline",$C$5:$C$32,"run_03",$D$5:$D$32,B56) | G56: =AVERAGE(D56:F56)
A57: M11 | B57: Planificación | C57: =COUNTIFS($B$5:$B$32,"Baseline",$D$5:$D$32,B57) | D57: =COUNTIFS($B$5:$B$32,"Pipeline",$C$5:$C$32,"run_01",$D$5:$D$32,B57) | E57: =COUNTIFS($B$5:$B$32,"Pipeline",$C$5:$C$32,"run_02",$D$5:$D$32,B57) | F57: =COUNTIFS($B$5:$B$32,"Pipeline",$C$5:$C$32,"run_03",$D$5:$D$32,B57) | G57: =AVERAGE(D57:F57)
A58: M11 | B58: Diseño | C58: =COUNTIFS($B$5:$B$32,"Baseline",$D$5:$D$32,B58) | D58: =COUNTIFS($B$5:$B$32,"Pipeline",$C$5:$C$32,"run_01",$D$5:$D$32,B58) | E58: =COUNTIFS($B$5:$B$32,"Pipeline",$C$5:$C$32,"run_02",$D$5:$D$32,B58) | F58: =COUNTIFS($B$5:$B$32,"Pipeline",$C$5:$C$32,"run_03",$D$5:$D$32,B58) | G58: =AVERAGE(D58:F58)
A59: M11 | B59: Sprint 1 | C59: =COUNTIFS($B$5:$B$32,"Baseline",$D$5:$D$32,B59) | D59: =COUNTIFS($B$5:$B$32,"Pipeline",$C$5:$C$32,"run_01",$D$5:$D$32,B59) | E59: =COUNTIFS($B$5:$B$32,"Pipeline",$C$5:$C$32,"run_02",$D$5:$D$32,B59) | F59: =COUNTIFS($B$5:$B$32,"Pipeline",$C$5:$C$32,"run_03",$D$5:$D$32,B59) | G59: =AVERAGE(D59:F59)
A60: M11 | B60: Sprint 2 | C60: =COUNTIFS($B$5:$B$32,"Baseline",$D$5:$D$32,B60) | D60: =COUNTIFS($B$5:$B$32,"Pipeline",$C$5:$C$32,"run_01",$D$5:$D$32,B60) | E60: =COUNTIFS($B$5:$B$32,"Pipeline",$C$5:$C$32,"run_02",$D$5:$D$32,B60) | F60: =COUNTIFS($B$5:$B$32,"Pipeline",$C$5:$C$32,"run_03",$D$5:$D$32,B60) | G60: =AVERAGE(D60:F60)
A61: M11 | B61: Sprint 3 | C61: =COUNTIFS($B$5:$B$32,"Baseline",$D$5:$D$32,B61) | D61: =COUNTIFS($B$5:$B$32,"Pipeline",$C$5:$C$32,"run_01",$D$5:$D$32,B61) | E61: =COUNTIFS($B$5:$B$32,"Pipeline",$C$5:$C$32,"run_02",$D$5:$D$32,B61) | F61: =COUNTIFS($B$5:$B$32,"Pipeline",$C$5:$C$32,"run_03",$D$5:$D$32,B61) | G61: =AVERAGE(D61:F61)
A63: M12 | B63: Coste de corrección total (min) | C63: =SUMIFS($H$5:$H$32,$B$5:$B$32,"Baseline") | D63: =SUMIFS($H$5:$H$32,$B$5:$B$32,"Pipeline",$C$5:$C$32,"run_01") | E63: =SUMIFS($H$5:$H$32,$B$5:$B$32,"Pipeline",$C$5:$C$32,"run_02") | F63: =SUMIFS($H$5:$H$32,$B$5:$B$32,"Pipeline",$C$5:$C$32,"run_03") | G63: =AVERAGE(D63:F63)
A64: M12 | B64: Coste de corrección total (min) | C64: =COUNTIFS($B$5:$B$32,"Baseline",$H$5:$H$32,">0") | D64: =COUNTIFS($B$5:$B$32,"Pipeline",$C$5:$C$32,"run_01",$H$5:$H$32,">0") | E64: =COUNTIFS($B$5:$B$32,"Pipeline",$C$5:$C$32,"run_02",$H$5:$H$32,">0") | F64: =COUNTIFS($B$5:$B$32,"Pipeline",$C$5:$C$32,"run_03",$H$5:$H$32,">0") | G64: =AVERAGE(D64:F64)

Sheet 08b_aux_bitacora_decisiones
A1: 08b — Bitácora auxiliar de decisiones del pipeline
A2: NO entra en H3 ni en métricas del contraste.
A4: Fecha | B4: Hito / Run | C4: Categoría | D4: Decisión / Evento metodológico | E4: Justificación breve | F4: Referencia bitácora
A5: 2026-04-24 | B5: Caso 02 → reinicio | C5: Reinicio controlado | D5: Diagnóstico del Caso 02 (pipeline previo bloqueado por descomposición en contratos congelados sobre brief de películas, no de Hundidos) y decisión de reinicio controlado del pipeline. | E5: Se detectó patrón de sobreingeniería: priorizar contratos antes que recorrido end-to-end. Reorientación a flujo por fases con agentes y validación humana. | F5: Bitácora 2026-04-24 (entrada 1).
A6: 2026-04-24 | B6: Caso 02 | C6: Decisión metodológica | D6: Definición de brief.md y gates humanos como elementos centrales del pipeline. | E6: Brief congelado como única fuente de verdad de entrada; gates humanos como puntos de control auditables. | F6: Bitácora 2026-04-24 (entrada 2).
A7: 2026-04-24 | B7: Caso 02 | C7: Decisión metodológica | D7: Congelación del pipeline_specs.md como documento técnico interno de especificación del pipeline. | E7: Materialización del principio de versión congelada hasheable. | F7: Bitácora 2026-04-24 (entrada 3).
A8: 2026-04-24 | B8: Caso 02 | C8: Decisión técnica | D8: Adopción de output_pydantic en tasks.yaml para validación inmediata de salidas del agente contra esquemas Pydantic. | E8: Elimina vía de alucinación al rechazar de forma estricta salidas no conformes al esquema. | F8: Bitácora 2026-04-24 (entrada 4).
A9: 2026-04-24 | B9: Caso 02 | C9: Construcción | D9: Preparación de la base técnica del pipeline (estructura de directorios, dependencias, configuración inicial). | E9: Fase preparatoria antes de implementar la primera crew. | F9: Bitácora 2026-04-24 (entrada 5).
A10: 2026-04-24 | B10: Caso 02 | C10: Construcción | D10: Implementación inicial de requisitos_crew (primer agente del pipeline). | E10: Prueba de concepto del patrón una-crew-por-fase con CrewAI. | F10: Bitácora 2026-04-24 (entradas 6-9).
A11: 2026-04-24 | B11: Caso 02 | C11: Decisión técnica | D11: Configuración Modelfile derivado (hundidos-analista) con parámetros bakeados: num_ctx=8192, temperature=0.2, top_p=0.9, seed=42. | E11: Trazabilidad apunta a artefacto hashable y no a argumentos pasados en tiempo de ejecución. | F11: Bitácora 2026-04-24 (entrada 10).
A12: 2026-04-24 | B12: Caso 02 | C12: Incidencia construcción | D12: Error de primera ejecución: Completions.create() got an unexpected keyword argument. Problema de compatibilidad del cliente con la API. | E12: Resuelto ajustando argumentos del cliente. Documentado pero no relevante para H3. | F12: Bitácora 2026-04-24 (entrada 11).
A13: 2026-04-25 | B13: Run 1 (Caso 02) | C13: Incidencia construcción | D13: Run 1 rechazado: el registro de requisitos cumple mínimos cuantitativos pero omite subsecciones del brief. | E13: Motivó la iteración del prompt del Analista para incluir reglas de cobertura cualitativa explícitas. | F13: Bitácora 2026-04-25 (cierre fase 01).
A14: 2026-04-25 | B14: Run 2 (Caso 02) | C14: Aceptación con observaciones | D14: Run 2 aceptado tras correcciones del prompt; el LLM 7B optimiza umbrales numéricos pero requiere reglas cualitativas explícitas. | E14: Confirmación del patrón: umbrales numéricos solos son insuficientes; hace falta listado enumerado de subsecciones esperadas. | F14: Bitácora 2026-04-25 (cierre fase 01).
A15: 2026-04-25 | B15: Plan fase 02 | C15: Plan | D15: Plan de implementación de la fase 02 (planificación) en el Flow. | E15: Apertura del ciclo de construcción del agente PM. | F15: Bitácora 2026-04-25 (plan fase 02).
... A38: 2026-05-17 | B38: Preflight + Re-congelación | C38: AJUSTE POST-CONGELACIÓN | D38: Preflight run_2026-05-17_18-49 falló por ModuleNotFoundError (módulo requests). Se reconstruyó .venv_Test con dependencias fijas (Django 3.2, Pillow 9.5.0, django-filter 23.1, requests 2.31.0). Además: ajuste del prompt de planificación (enriquecimiento de entregable_verificable y reubicación de riesgos por sprint). | E38: Constituye una RE-CONGELACIÓN EFECTIVA del 17/05. Las 3 runs oficiales (18-19 mayo) corren sobre esta versión. Pendiente: actualizar TFG §3.4 regla 8 y §6.3.2 reemplazando "2026-05-15" por "2026-05-17". | F38: Bitácora 2026-05-17 (preflight + ajuste planificación).

Sheet 09_VD5_reproducibilidad
A1: VD5 — Reproducibilidad caso IA (M19, M20, M21) — solo pipeline
A2: Solo aplica al pipeline. Una columna por run. M19 = artefactos esperados producidos con evidencia completa. M20 = elementos regenerables (entorno, pipeline, suite). M21 = resultados con versión/hash enlazado.
A4: M19 — Artefactos esperados con evidencia completa
A5: Artefacto esperado | B5: Run 01 | C5: Run 02 | D5: Run 03
A6: manifest.json | B6: Sí | C6: Sí | D6: Sí
A7: run_summary.json | B7: Sí | C7: Sí | D7: Sí
A8: registro_requisitos.json | B8: Sí | C8: Sí | D8: Sí
A9: backlog.json | B9: Sí | C9: Sí | D9: Sí
A10: plan_sprints.json | B10: Sí | C10: Sí | D10: Sí
A11: riesgos.json | B11: Sí | C11: Sí | D11: Sí
A12: diseno_tecnico.json | B12: Sí | C12: Sí | D12: Sí
A13: review_sprint_1.json | B13: Sí | C13: Sí | D13: Sí
A14: review_sprint_2.json | B14: Sí | C14: Sí | D14: Sí
A15: review_sprint_3.json | B15: Sí | C15: Sí | D15: Sí
A16: validacion_final.json | B16: Sí | C16: Sí | D16: Sí
... A19: readme.md | B19: Sí | C19: Sí | D19: Sí
A20: N total artefactos esperados | B20: 14 | C20: 14 | D20: 14
A21: N con evidencia completa (Sí) | B21: =COUNTIF(B6:B19,"Sí") | C21: =COUNTIF(C6:C19,"Sí") | D21: =COUNTIF(D6:D19,"Sí")
A22: M19 (%) | B22: =IF(B20>0,B21/B20*100,0) | C22: =IF(C20>0,C21/C20*100,0) | D22: =IF(D20>0,D21/D20*100,0)
A25: M20 — Regenerabilidad
A26: Elemento | B26: Run 01 | C26: Run 02 | D26: Run 03
A27: Entorno reproducible | B27: Sí | C27: Sí | D27: Sí
A28: Pipeline completo regenerable | B28: Sí | C28: Sí | D28: Sí
A29: Suite de tests regenerable | B29: Parcial | C29: Parcial | D29: Parcial
A30: M20 (%) | B30: =COUNTIF(B27:B29,"Sí")/3*100 | C30: =COUNTIF(C27:C29,"Sí")/3*100 | D30: =COUNTIF(D27:D29,"Sí")/3*100
A33: M21 — Trazabilidad versión-resultado
A34: Resultado | B34: Run 01 | C34: Run 02 | D34: Run 03
A35: Artefactos fase Requisitos | B35: Sí | C35: Sí | D35: Sí
A36: Artefactos Planificación | B36: Sí | C36: Sí | D36: Sí
A37: Artefactos Diseño | B37: Sí | C37: Sí | D37: Sí
A38: Entregables sprint | B38: Sí | C38: Sí | D38: Sí
A39: Validación final | B39: Sí | C39: Sí | D39: Sí
A40: M21 (%) | B40: =COUNTIF(B35:B39,"Sí")/5*100 | C40: =COUNTIF(C35:C39,"Sí")/5*100 | D40: =COUNTIF(D35:D39,"Sí")/5*100

Sheet 10_AGREGADOS
A1: Resultados agregados por hipótesis
A2: Esta hoja consolida los resultados de las hojas anteriores para alimentar el análisis de resultados de la memoria.
A4: H2 — Calidad de artefactos (M1, M3, M4 por familia)
A5: Familia | B5: Métrica | C5: Baseline | D5: Pipeline media (3 runs) | E5: Pipeline rango (min-max) | F5: Dirección (= IA≥B, < IA<B)
A6: Requisitos | B6: M1 | C6: =IFERROR(AVERAGEIFS('02_R1_sintesis_artefactos'!F:F,'02_R1_sintesis_artefactos'!B:B,"Baseline",'02_R1_sintesis_artefactos'!D:D,"Requisitos"),"—") | D6: =IFERROR(AVERAGEIFS('02_R1_sintesis_artefactos'!F:F,'02_R1_sintesis_artefactos'!B:B,"Pipeline",'02_R1_sintesis_artefactos'!D:D,"Requisitos"),"—") | E6: =IFERROR(_xlfn.MINIFS('02_R1_sintesis_artefactos'!F:F,'02_R1_sintesis_artefactos'!B:B,"Pipeline",'02_R1_sintesis_artefactos'!D:D,"Requisitos")&" - "&_xlfn.MAXIFS('02_R1_sintesis_artefactos'!F:F,'02_R1_sintesis_artefactos'!B:B,"Pipeline",'02_R1_sintesis_artefactos'!D:D,"Requisitos"),"—") | F6: =IF(OR(C6="—",D6="—"),"—",IF(D6>=C6,"= IA≥B (favorable)","< IA<B (desfavorable)"))
A7: Requisitos | B7: M3 | C7: =IFERROR(AVERAGEIFS('02_R1_sintesis_artefactos'!H:H,'02_R1_sintesis_artefactos'!B:B,"Baseline",'02_R1_sintesis_artefactos'!D:D,"Requisitos"),"—") | D7: =IFERROR(AVERAGEIFS('02_R1_sintesis_artefactos'!H:H,'02_R1_sintesis_artefactos'!B:B,"Pipeline",'02_R1_sintesis_artefactos'!D:D,"Requisitos"),"—") | E7: =IFERROR(_xlfn.MINIFS('02_R1_sintesis_artefactos'!H:H,'02_R1_sintesis_artefactos'!B:B,"Pipeline",'02_R1_sintesis_artefactos'!D:D,"Requisitos")&" - "&_xlfn.MAXIFS('02_R1_sintesis_artefactos'!H:H,'02_R1_sintesis_artefactos'!B:B,"Pipeline",'02_R1_sintesis_artefactos'!D:D,"Requisitos"),"—") | F7: =IF(OR(C7="—",D7="—"),"—",IF(D7>=C7,"= IA≥B (favorable)","< IA<B (desfavorable)"))
A8: Requisitos | B8: M4 (%) | C8: =IFERROR(AVERAGEIFS('02_R1_sintesis_artefactos'!M:M,'02_R1_sintesis_artefactos'!B:B,"Baseline",'02_R1_sintesis_artefactos'!D:D,"Requisitos"),"—") | D8: =IFERROR(AVERAGEIFS('02_R1_sintesis_artefactos'!M:M,'02_R1_sintesis_artefactos'!B:B,"Pipeline",'02_R1_sintesis_artefactos'!D:D,"Requisitos"),"—") | E8: =IFERROR(_xlfn.MINIFS('02_R1_sintesis_artefactos'!M:M,'02_R1_sintesis_artefactos'!B:B,"Pipeline",'02_R1_sintesis_artefactos'!D:D,"Requisitos")&" - "&_xlfn.MAXIFS('02_R1_sintesis_artefactos'!M:M,'02_R1_sintesis_artefactos'!B:B,"Pipeline",'02_R1_sintesis_artefactos'!D:D,"Requisitos"),"—") | F8: =IF(OR(C8="—",D8="—"),"—",IF(D8>=C8,"= IA≥B (favorable)","< IA<B (desfavorable)"))
A9: Planificación | B9: M1 | C9: =IFERROR(AVERAGEIFS('02_R1_sintesis_artefactos'!F:F,'02_R1_sintesis_artefactos'!B:B,"Baseline",'02_R1_sintesis_artefactos'!D:D,"Planificación"),"—") | D9: =IFERROR(AVERAGEIFS('02_R1_sintesis_artefactos'!F:F,'02_R1_sintesis_artefactos'!B:B,"Pipeline",'02_R1_sintesis_artefactos'!D:D,"Planificación"),"—") | E9: =IFERROR(_xlfn.MINIFS('02_R1_sintesis_artefactos'!F:F,'02_R1_sintesis_artefactos'!B:B,"Pipeline",'02_R1_sintesis_artefactos'!D:D,"Planificación")&" - "&_xlfn.MAXIFS('02_R1_sintesis_artefactos'!F:F,'02_R1_sintesis_artefactos'!B:B,"Pipeline",'02_R1_sintesis_artefactos'!D:D,"Planificación"),"—") | F9: =IF(OR(C9="—",D9="—"),"—",IF(D9>=C9,"= IA≥B (favorable)","< IA<B (desfavorable)"))
A10: Planificación | B10: M3 | C10: =IFERROR(AVERAGEIFS('02_R1_sintesis_artefactos'!H:H,'02_R1_sintesis_artefactos'!B:B,"Baseline",'02_R1_sintesis_artefactos'!D:D,"Planificación"),"—") | D10: =IFERROR(AVERAGEIFS('02_R1_sintesis_artefactos'!H:H,'02_R1_sintesis_artefactos'!B:B,"Pipeline",'02_R1_sintesis_artefactos'!D:D,"Planificación"),"—") | E10: =IFERROR(_xlfn.MINIFS('02_R1_sintesis_artefactos'!H:H,'02_R1_sintesis_artefactos'!B:B,"Pipeline",'02_R1_sintesis_artefactos'!D:D,"Planificación")&" - "&_xlfn.MAXIFS('02_R1_sintesis_artefactos'!H:H,'02_R1_sintesis_artefactos'!B:B,"Pipeline",'02_R1_sintesis_artefactos'!D:D,"Planificación"),"—") | F10: =IF(OR(C10="—",D10="—"),"—",IF(D10>=C10,"= IA≥B (favorable)","< IA<B (desfavorable)"))
A11: Planificación | B11: M4 (%) | C11: =IFERROR(AVERAGEIFS('02_R1_sintesis_artefactos'!M:M,'02_R1_sintesis_artefactos'!B:B,"Baseline",'02_R1_sintesis_artefactos'!D:D,"Planificación"),"—") | D11: =IFERROR(AVERAGEIFS('02_R1_sintesis_artefactos'!M:M,'02_R1_sintesis_artefactos'!B:B,"Pipeline",'02_R1_sintesis_artefactos'!D:D,"Planificación"),"—") | E11: =IFERROR(_xlfn.MINIFS('02_R1_sintesis_artefactos'!M:M,'02_R1_sintesis_artefactos'!B:B,"Pipeline",'02_R1_sintesis_artefactos'!D:D,"Planificación")&" - "&_xlfn.MAXIFS('02_R1_sintesis_artefactos'!M:M,'02_R1_sintesis_artefactos'!B:B,"Pipeline",'02_R1_sintesis_artefactos'!D:D,"Planificación"),"—") | F11: =IF(OR(C11="—",D11="—"),"—",IF(D11>=C11,"= IA≥B (favorable)","< IA<B (desfavorable)"))
A12: Diseño técnico | B12: M1 | C12: =IFERROR(AVERAGEIFS('02_R1_sintesis_artefactos'!F:F,'02_R1_sintesis_artefactos'!B:B,"Baseline",'02_R1_sintesis_artefactos'!D:D,"Diseño técnico"),"—") | D12: =IFERROR(AVERAGEIFS('02_R1_sintesis_artefactos'!F:F,'02_R1_sintesis_artefactos'!B:B,"Pipeline",'02_R1_sintesis_artefactos'!D:D,"Diseño técnico"),"—") | E12: =IFERROR(_xlfn.MINIFS('02_R1_sintesis_artefactos'!F:F,'02_R1_sintesis_artefactos'!B:B,"Pipeline",'02_R1_sintesis_artefactos'!D:D,"Diseño técnico")&" - "&_xlfn.MAXIFS('02_R1_sintesis_artefactos'!F:F,'02_R1_sintesis_artefactos'!B:B,"Pipeline",'02_R1_sintesis_artefactos'!D:D,"Diseño técnico"),"—") | F12: =IF(OR(C12="—",D12="—"),"—",IF(D12>=C12,"= IA≥B (favorable)","< IA<B (desfavorable)"))
A13: Diseño técnico | B13: M3 | C13: =IFERROR(AVERAGEIFS('02_R1_sintesis_artefactos'!H:H,'02_R1_sintesis_artefactos'!B:B,"Baseline",'02_R1_sintesis_artefactos'!D:D,"Diseño técnico"),"—") | D13: =IFERROR(AVERAGEIFS('02_R1_sintesis_artefactos'!H:H,'02_R1_sintesis_artefactos'!B:B,"Pipeline",'02_R1_sintesis_artefactos'!D:D,"Diseño técnico"),"—") | E13: =IFERROR(_xlfn.MINIFS('02_R1_sintesis_artefactos'!H:H,'02_R1_sintesis_artefactos'!B:B,"Pipeline",'02_R1_sintesis_artefactos'!D:D,"Diseño técnico")&" - "&_xlfn.MAXIFS('02_R1_sintesis_artefactos'!H:H,'02_R1_sintesis_artefactos'!B:B,"Pipeline",'02_R1_sintesis_artefactos'!D:D,"Diseño técnico"),"—") | F13: =IF(OR(C13="—",D13="—"),"—",IF(D13>=C13,"= IA≥B (favorable)","< IA<B (desfavorable)"))
A14: Diseño técnico | B14: M4 (%) | C14: =IFERROR(AVERAGEIFS('02_R1_sintesis_artefactos'!M:M,'02_R1_sintesis_artefactos'!B:B,"Baseline",'02_R1_sintesis_artefactos'!D:D,"Diseño técnico"),"—") | D14: =IFERROR(AVERAGEIFS('02_R1_sintesis_artefactos'!M:M,'02_R1_sintesis_artefactos'!B:B,"Pipeline",'02_R1_sintesis_artefactos'!D:D,"Diseño técnico"),"—") | E14: =IFERROR(_xlfn.MINIFS('02_R1_sintesis_artefactos'!M:M,'02_R1_sintesis_artefactos'!B:B,"Pipeline",'02_R1_sintesis_artefactos'!D:D,"Diseño técnico")&" - "&_xlfn.MAXIFS('02_R1_sintesis_artefactos'!M:M,'02_R1_sintesis_artefactos'!B:B,"Pipeline",'02_R1_sintesis_artefactos'!D:D,"Diseño técnico"),"—") | F14: =IF(OR(C14="—",D14="—"),"—",IF(D14>=C14,"= IA≥B (favorable)","< IA<B (desfavorable)"))
A15: Seguimiento | B15: M1 | C15: =IFERROR(AVERAGEIFS('02_R1_sintesis_artefactos'!F:F,'02_R1_sintesis_artefactos'!B:B,"Baseline",'02_R1_sintesis_artefactos'!D:D,"Seguimiento"),"—") | D15: =IFERROR(AVERAGEIFS('02_R1_sintesis_artefactos'!F:F,'02_R1_sintesis_artefactos'!B:B,"Pipeline",'02_R1_sintesis_artefactos'!D:D,"Seguimiento"),"—") | E15: =IFERROR(_xlfn.MINIFS('02_R1_sintesis_artefactos'!F:F,'02_R1_sintesis_artefactos'!B:B,"Pipeline",'02_R1_sintesis_artefactos'!D:D,"Seguimiento")&" - "&_xlfn.MAXIFS('02_R1_sintesis_artefactos'!F:F,'02_R1_sintesis_artefactos'!B:B,"Pipeline",'02_R1_sintesis_artefactos'!D:D,"Seguimiento"),"—") | F15: =IF(OR(C15="—",D15="—"),"—",IF(D15>=C15,"= IA≥B (favorable)","< IA<B (desfavorable)"))
A16: Seguimiento | B16: M3 | C16: =IFERROR(AVERAGEIFS('02_R1_sintesis_artefactos'!H:H,'02_R1_sintesis_artefactos'!B:B,"Baseline",'02_R1_sintesis_artefactos'!D:D,"Seguimiento"),"—") | D16: =IFERROR(AVERAGEIFS('02_R1_sintesis_artefactos'!H:H,'02_R1_sintesis_artefactos'!B:B,"Pipeline",'02_R1_sintesis_artefactos'!D:D,"Seguimiento"),"—") | E16: =IFERROR(_xlfn.MINIFS('02_R1_sintesis_artefactos'!H:H,'02_R1_sintesis_artefactos'!B:B,"Pipeline",'02_R1_sintesis_artefactos'!D:D,"Seguimiento")&" - "&_xlfn.MAXIFS('02_R1_sintesis_artefactos'!H:H,'02_R1_sintesis_artefactos'!B:B,"Pipeline",'02_R1_sintesis_artefactos'!D:D,"Seguimiento"),"—") | F16: =IF(OR(C16="—",D16="—"),"—",IF(D16>=C16,"= IA≥B (favorable)","< IA<B (desfavorable)"))
A17: Seguimiento | B17: M4 (%) | C17: =IFERROR(SUMIFS('02_R1_sintesis_artefactos'!L:L,'02_R1_sintesis_artefactos'!B:B,"Baseline",'02_R1_sintesis_artefactos'!D:D,"Seguimiento")/SUMIFS('02_R1_sintesis_artefactos'!K:K,'02_R1_sintesis_artefactos'!B:B,"Baseline",'02_R1_sintesis_artefactos'!D:D,"Seguimiento")*100,"—") | D17: =IFERROR(AVERAGE(SUMIFS('02_R1_sintesis_artefactos'!L:L,'02_R1_sintesis_artefactos'!B:B,"Pipeline",'02_R1_sintesis_artefactos'!C:C,"run_01",'02_R1_sintesis_artefactos'!D:D,"Seguimiento")/SUMIFS('02_R1_sintesis_artefactos'!K:K,'02_R1_sintesis_artefactos'!B:B,"Pipeline",'02_R1_sintesis_artefactos'!C:C,"run_01",'02_R1_sintesis_artefactos'!D:D,"Seguimiento")*100,SUMIFS('02_R1_sintesis_artefactos'!L:L,'02_R1_sintesis_artefactos'!B:B,"Pipeline",'02_R1_sintesis_artefactos'!C:C,"run_02",'02_R1_sintesis_artefactos'!D:D,"Seguimiento")/SUMIFS('02_R1_sintesis_artefactos'!K:K,'02_R1_sintesis_artefactos'!B:B,"Pipeline",'02_R1_sintesis_artefactos'!C:C,"run_02",'02_R1_sintesis_artefactos'!D:D,"Seguimiento")*100,SUMIFS('02_R1_sintesis_artefactos'!L:L,'02_R1_sintesis_artefactos'!B:B,"Pipeline",'02_R1_sintesis_artefactos'!C:C,"run_03",'02_R1_sintesis_artefactos'!D:D,"Seguimiento")/SUMIFS('02_R1_sintesis_artefactos'!K:K,'02_R1_sintesis_artefactos'!B:B,"Pipeline",'02_R1_sintesis_artefactos'!C:C,"run_03",'02_R1_sintesis_artefactos'!D:D,"Seguimiento")*100),"—") | E17: =IFERROR(_xlfn.MINIFS('02_R1_sintesis_artefactos'!M:M,'02_R1_sintesis_artefactos'!B:B,"Pipeline",'02_R1_sintesis_artefactos'!D:D,"Seguimiento")&" - "&_xlfn.MAXIFS('02_R1_sintesis_artefactos'!M:M,'02_R1_sintesis_artefactos'!B:B,"Pipeline",'02_R1_sintesis_artefactos'!D:D,"Seguimiento"),"—") | F17: =IF(OR(C17="—",D17="—"),"—",IF(D17>=C17,"= IA≥B (favorable)","< IA<B (desfavorable)"))
A18: Cierre | B18: M1 | C18: =IFERROR(AVERAGEIFS('02_R1_sintesis_artefactos'!F:F,'02_R1_sintesis_artefactos'!B:B,"Baseline",'02_R1_sintesis_artefactos'!D:D,"Cierre"),"—") | D18: =IFERROR(AVERAGEIFS('02_R1_sintesis_artefactos'!F:F,'02_R1_sintesis_artefactos'!B:B,"Pipeline",'02_R1_sintesis_artefactos'!D:D,"Cierre"),"—") | E18: =IFERROR(_xlfn.MINIFS('02_R1_sintesis_artefactos'!F:F,'02_R1_sintesis_artefactos'!B:B,"Pipeline",'02_R1_sintesis_artefactos'!D:D,"Cierre")&" - "&_xlfn.MAXIFS('02_R1_sintesis_artefactos'!F:F,'02_R1_sintesis_artefactos'!B:B,"Pipeline",'02_R1_sintesis_artefactos'!D:D,"Cierre"),"—") | F18: =IF(OR(C18="—",D18="—"),"—",IF(D18>=C18,"= IA≥B (favorable)","< IA<B (desfavorable)"))
A19: Cierre | B19: M3 | C19: =IFERROR(AVERAGEIFS('02_R1_sintesis_artefactos'!H:H,'02_R1_sintesis_artefactos'!B:B,"Baseline",'02_R1_sintesis_artefactos'!D:D,"Cierre"),"—") | D19: =IFERROR(AVERAGEIFS('02_R1_sintesis_artefactos'!H:H,'02_R1_sintesis_artefactos'!B:B,"Pipeline",'02_R1_sintesis_artefactos'!D:D,"Cierre"),"—") | E19: =IFERROR(_xlfn.MINIFS('02_R1_sintesis_artefactos'!H:H,'02_R1_sintesis_artefactos'!B:B,"Pipeline",'02_R1_sintesis_artefactos'!D:D,"Cierre")&" - "&_xlfn.MAXIFS('02_R1_sintesis_artefactos'!H:H,'02_R1_sintesis_artefactos'!B:B,"Pipeline",'02_R1_sintesis_artefactos'!D:D,"Cierre"),"—") | F19: =IF(OR(C19="—",D19="—"),"—",IF(D19>=C19,"= IA≥B (favorable)","< IA<B (desfavorable)"))
A20: Cierre | B20: M4 (%) | C20: =IFERROR(AVERAGEIFS('02_R1_sintesis_artefactos'!M:M,'02_R1_sintesis_artefactos'!B:B,"Baseline",'02_R1_sintesis_artefactos'!D:D,"Cierre"),"—") | D20: =IFERROR(AVERAGEIFS('02_R1_sintesis_artefactos'!M:M,'02_R1_sintesis_artefactos'!B:B,"Pipeline",'02_R1_sintesis_artefactos'!D:D,"Cierre"),"—") | E20: =IFERROR(_xlfn.MINIFS('02_R1_sintesis_artefactos'!M:M,'02_R1_sintesis_artefactos'!B:B,"Pipeline",'02_R1_sintesis_artefactos'!D:D,"Cierre")&" - "&_xlfn.MAXIFS('02_R1_sintesis_artefactos'!M:M,'02_R1_sintesis_artefactos'!B:B,"Pipeline",'02_R1_sintesis_artefactos'!D:D,"Cierre"),"—") | F20: =IF(OR(C20="—",D20="—"),"—",IF(D20>=C20,"= IA≥B (favorable)","< IA<B (desfavorable)"))
A23: VEREDICTO H2 — Sin diferencia sustantiva en M1/M3/M4 a través de las 5 familias
A24: Anotar manualmente la lectura cualitativa (no se calcula porque exige juicio cualitativo sobre 'sustantiva')
A30: H1 — Esfuerzo humano: consultar 07_T1_T2_T3_tiempos (M17)
A31: H3 — Deriva: consultar 08_I1_incidencias (M14 y auxiliares M9-M13)
A32: VD2 — Calidad mínima del producto: consultar 06_P1_P2_pruebas (M6, M7, M-operatividad)
A34: VD5 — Reproducibilidad caso IA
A35: Métrica | B35: Run 01 | C35: Run 02 | D35: Run 03 | E35: Media
A36: M19 (%) — Evidencia completa | B36: ='09_VD5_reproducibilidad'!B22 | C36: ='09_VD5_reproducibilidad'!C22 | D36: ='09_VD5_reproducibilidad'!D22 | E36: =AVERAGE(B36:D36)
A37: M20 (%) — Regenerabilidad | B37: ='09_VD5_reproducibilidad'!B30 | C37: ='09_VD5_reproducibilidad'!C30 | D37: ='09_VD5_reproducibilidad'!D30 | E37: =AVERAGE(B37:D37)
A38: M21 (%) — Trazabilidad versión-resultado | B38: ='09_VD5_reproducibilidad'!B40 | C38: ='09_VD5_reproducibilidad'!C40 | D38: ='09_VD5_reproducibilidad'!D40 | E38: =AVERAGE(B38:D38)
A40: Métricas descriptivas caso IA (M8, M13, M16)
A41: Métricas descriptivas del pipeline (NO soportan hipótesis del contraste). M8 = tasa de aprobación en gates. M13 = % de incidencias detectadas en gate humano. M16 = tiempo activo de elaboración por fase. M18 = iteraciones/revisiones adicionales por gate cuando existe evidencia.
A43: Métrica | B43: Run 01 | C43: Run 02 | D43: Run 03 | E43: Media
A44: Gates aprobados (input) | B44: 3 | C44: 2 | D44: 3 | E44: —
A45: Gates ejecutados por run | B45: 3 | C45: 3 | D45: 3 | E45: —
A46: M8 (%) — Tasa de aprobación en gates | B46: =IF(B45>0,B44/B45*100,0) | C46: =IF(C45>0,C44/C45*100,0) | D46: =IF(D45>0,D44/D45*100,0) | E46: =AVERAGE(B46:D46)
A47: M16 — Tiempo activo IA por fase (min) | B47: ='07_T1_T2_T3_tiempos'!C42 | C47: ='07_T1_T2_T3_tiempos'!D42 | D47: ='07_T1_T2_T3_tiempos'!E42 | E47: =AVERAGE(B47:D47)
A48: M13 (%) — Incidencias detectadas por gate humano | B48: ='08_I1_incidencias'!C39 | C48: ='08_I1_incidencias'!D39 | D48: ='08_I1_incidencias'!E39 | E48: ='08_I1_incidencias'!F39
A49: Nota: M13 enlaza con la fila 39 de 08_I1_incidencias. M16 enlaza con la fila 42 de 07_T1_T2_T3_tiempos.
A50: M18 — Iteraciones/revisiones adicionales de gate (proxy) | B50: =B45-B44 | C50: =C45-C44 | D50: =D45-D44 | E50: =AVERAGE(B50:D50)
